Workbook
Name IQ_CH: 110000
Name IQ_CQ: 5000
Name IQ_CY: 10000
Name IQ_DAILY: 500000
Name IQ_FH: 100000
Name IQ_FQ: 500
Name IQ_FY: 1000
Name IQ_LTM: 2000
Name IQ_MONTH: 15000
Name IQ_NTM: 6000
Name IQ_WEEK: 50000
Name IQ_YTD: 3000

Sheet Data Sheet 
A2: COMPANY NAME | B2: RELIANCE INDUSTRIES LTD | E2: =IF(B3<>B4, "A NEW VERSION OF THE WORKSHEET IS AVAILABLE", "")
A3: LATEST VERSION | B3: 2.1 | E3: PLEASE DO NOT MAKE ANY CHANGES TO THIS SHEET
A4: CURRENT VERSION | B4: 2.1
A6: META
A7: Number of shares | B7: =IF(B10>0, B10/B9, 0) -> 1353.8808
A8: Face Value | B8: 10
A9: Current Price | B9: 1279
A10: Market Capitalization | B10: 1731613.6
A16: PROFIT & LOSS
A17: Report Date | B17: 42825 | C17: 43190 | D17: 43555 | E17: 43921 | F17: 44286 | G17: 44651 | H17: 45016 | I17: 45382 | J17: 45747 | K17: 46112
A18: Sales | B18: 303954 | C18: 390823 | D18: 568337 | E18: 596679 | F18: 466307 | G18: 694673 | H18: 876396 | I18: 899041 | J18: 962820 | K18: 1055780
A19: Raw Material Cost | B19: 217518 | C19: 276076 | D19: 399167 | E19: 410288 | F19: 301765 | G19: 494449 | H19: 618746 | I19: 590226 | J19: 644813 | K19: 698930
A20: Change in Inventory | B20: 5218 | C20: 8610 | D20: 4680 | E20: 5048 | F20: 9064 | G20: 21457 | H20: 30263 | I20: 4883 | J20: 15124 | K20: 10267
A21: Power and Fuel | B21: 11251 | C21: 14569 | D21: 17029 | E21: 15098 | F21: 13214 | G21: 17902 | H21: 25062 | I21: 22137 | J21: 23823 | K21: 22069
A22: Other Mfr. Exp | B22: 9909 | C22: 9691 | D22: 12198 | E22: 11434 | F22: 7687 | G22: 12174 | H22: 19658 | I22: 18276 | J22: 18358 | K22: 21162
A23: Employee Cost | B23: 8388 | C23: 9523 | D23: 12488 | E23: 14075 | F23: 14817 | G23: 18758 | H23: 24872 | I23: 25679 | J23: 28559 | K23: 30318
A24: Selling and admin | B24: 18520 | C24: 29111 | D24: 50221 | E24: 62622 | F24: 56154 | G24: 63513 | H24: 67369 | I24: 77292 | J24: 88760 | K24: 104723
A25: Other Expenses | B25: -2721 | C25: -3852 | D25: -2336 | E25: -1056 | F25: 944 | G25: 753 | H25: 8634 | I25: 7816 | J25: 8033 | K25: 9780
A26: Other Income | B26: 9222 | C26: 9869 | D26: 8406 | E26: 8570 | F26: 22432 | G26: 19600 | H26: 12020 | I26: 15792 | J26: 17824 | K26: 28846
A27: Depreciation | B27: 11646 | C27: 16706 | D27: 20934 | E27: 22203 | F27: 26572 | G27: 29782 | H27: 40303 | I27: 50832 | J27: 53136 | K27: 57688
A28: Interest | B28: 3849 | C28: 8052 | D28: 16495 | E28: 22027 | F28: 21189 | G28: 14584 | H28: 19571 | I28: 23118 | J28: 24269 | K28: 27061
... A32: Dividend Amount | B32: 3254.9 | C32: 3553.2 | D32: 3851.9 | E32: 4120.35 | F32: 4511.5 | G32: 5412 | H32: 6089.4 | I32: 6766 | J32: 7442.6 | K32: 8119.2
A41: Quarters
A42: Report Date | B42: 45382 | C42: 45473 | D42: 45565 | E42: 45657 | F42: 45747 | G42: 45838 | H42: 45930 | I42: 46022 | J42: 46112 | K42: 46203
A43: Sales | B43: 236533 | C43: 231784 | D43: 231535 | E43: 239986 | F43: 261388 | G43: 243632 | H43: 254623 | I43: 264905 | J43: 294059 | K43: 309468
A44: Expenses | B44: 194017 | C44: 193019 | D44: 192477 | E44: 196197 | F44: 217556 | G44: 200727 | H44: 208738 | I44: 218887 | J44: 249918 | K44: 261951
A45: Other Income | B45: 4534 | C45: 3983 | D45: 4876 | E45: 4214 | F45: 4905 | G45: 15119 | H45: 4482 | I45: 4914 | J45: 4447 | K45: 6550
A46: Depreciation | B46: 13569 | C46: 13596 | D46: 12880 | E46: 13181 | F46: 13479 | G46: 13842 | H46: 14416 | I46: 14622 | J46: 14808 | K46: 15100
A47: Interest | B47: 5761 | C47: 5918 | D47: 6017 | E47: 6179 | F47: 6155 | G47: 7036 | H47: 6827 | I47: 6613 | J47: 6585 | K47: 8337
A48: Profit before tax | B48: 27720 | C48: 23234 | D48: 25037 | E48: 28643 | F48: 29103 | G48: 37146 | H48: 29124 | I48: 29697 | J48: 27195 | K48: 30630
A49: Tax | B49: 6577 | C49: 5786 | D49: 5936 | E49: 6839 | F49: 6669 | G49: 6465 | H49: 6978 | I49: 7530 | J49: 6579 | K49: 7629
A50: Net profit | B50: 18951 | C50: 15138 | D50: 16563 | E50: 18540 | F50: 19407 | G50: 26994 | H50: 18165 | I50: 18645 | J50: 16971 | K50: 20946
A51: Operating Profit | B51: 42516 | C51: 38765 | D51: 39058 | E51: 43789 | F51: 43832 | G51: 42905 | H51: 45885 | I51: 46018 | J51: 44141 | K51: 47517
A56: BALANCE SHEET
A57: Report Date | B57: 42825 | C57: 43190 | D57: 43555 | E57: 43921 | F57: 44286 | G57: 44651 | H57: 45016 | I57: 45382 | J57: 45747 | K57: 46112
A58: Equity Share Capital | B58: 2959 | C58: 5922 | D58: 5926 | E58: 6339 | F58: 6445 | G58: 6765 | H58: 6766 | I58: 6766 | J58: 13532 | K58: 13532
A59: Reserves | B59: 260750 | C59: 287584 | D59: 381186 | E59: 442827 | F59: 693727 | G59: 772720 | H59: 709106 | I59: 786715 | J59: 829668 | K59: 890498
A60: Borrowings | B60: 217475 | C60: 239843 | D60: 307714 | E60: 355133 | F60: 278962 | G60: 319158 | H60: 451664 | I60: 350719 | J60: 374313 | K60: 402962
A61: Other Liabilities | B61: 225618 | C61: 277924 | D61: 302804 | E61: 358716 | F61: 340931 | G61: 399979 | H61: 438346 | I61: 610848 | J61: 732200 | K61: 870554
A62: Total | B62: 706802 | C62: 811273 | D62: 997630 | E62: 1163015 | F62: 1320065 | G62: 1498622 | H62: 1605882 | I62: 1755048 | J62: 1949713 | K62: 2177546
A63: Net Block | B63: 198526 | C63: 403885 | D63: 398374 | E63: 532658 | F63: 541258 | G63: 627798 | H63: 724805 | I63: 779985 | J63: 999393 | K63: 1124795
A64: Capital Work in Progress | B64: 324837 | C64: 187022 | D64: 179463 | E64: 109106 | F64: 125953 | G64: 172506 | H64: 293752 | I64: 338855 | J64: 262358 | K64: 237686
A65: Investments | B65: 82899 | C65: 82862 | D65: 235635 | E65: 276767 | F65: 364828 | G65: 394264 | H65: 235560 | I65: 225672 | J65: 242381 | K65: 248332
A66: Other Assets | B66: 100540 | C66: 137504 | D66: 184158 | E66: 244484 | F66: 288026 | G66: 304054 | H66: 351765 | I66: 410536 | J66: 445581 | K66: 566733
A67: Total | B67: 706802 | C67: 811273 | D67: 997630 | E67: 1163015 | F67: 1320065 | G67: 1498622 | H67: 1605882 | I67: 1755048 | J67: 1949713 | K67: 2177546
A68: Receivables | B68: 8177 | C68: 17555 | D68: 30089 | E68: 19656 | F68: 19014 | G68: 23640 | H68: 28448 | I68: 31628 | J68: 42121 | K68: 58491
... A71: No. of Equity Shares | B71: 2958924277 | C71: 5921826196 | D71: 5925868997 | E71: 6338693823 | F71: 6762068814 | G71: 6765994014 | H71: 6766094014 | I71: 6766094014 | J71: 13532515463 | K71: 13532472634
A72: New Bonus Shares | C72: 2959863235 | D72: 2959863235 | J72: 6766186449 | K72: 11955084287
A73: Face value | B73: 10 | C73: 10 | D73: 10 | E73: 10 | F73: 10 | G73: 10 | H73: 10 | I73: 10 | J73: 10 | K73: 10
A81: CASH FLOW:
A82: Report Date | B82: 42825 | C82: 43190 | D82: 43555 | E82: 43921 | F82: 44286 | G82: 44651 | H82: 45016 | I82: 45382 | J82: 45747 | K82: 46112
A83: Cash from Operating Activity | B83: 49550 | C83: 71459 | D83: 42346 | E83: 94877 | F83: 26958 | G83: 110654 | H83: 115032 | I83: 158788 | J83: 178703 | K83: 192113
A84: Cash from Investing Activity | B84: -66201 | C84: -68192 | D84: -94507 | E84: -72497 | F84: -142385 | G84: -109162 | H84: -93001 | I84: -113581 | J84: -137535 | K84: -101089
A85: Cash from Financing Activity | B85: 8617 | C85: -2001 | D85: 55906 | E85: -2541 | F85: 101904 | G85: 17289 | H85: 10455 | I85: -16646 | J85: -31891 | K85: -51549
A86: Net Cash Flow | B86: -8034 | C86: 1266 | D86: 3745 | E86: 19839 | F86: -13523 | G86: 18781 | H86: 32486 | I86: 28561 | J86: 9277 | K86: 39475
A91: PRICE: | B91: 300.09 | C91: 401.08 | D91: 619.43 | E91: 506.06 | F91: 918.78 | G91: 1208.51 | H91: 1069.21 | I91: 1485.85 | J91: 1275.1 | K91: 1343.9
A93: DERIVED:
A94: Adjusted Equity Shares in Cr | B94: 1387.22 | C94: 1351.39 | D94: 1352.26 | E94: 1352.37 | F94: 1267.89 | G94: 1352.98 | H94: 1353.12 | I94: 1353.14 | J94: 1353.24 | K94: 1353.25

Sheet HistoricalFS
B8: ="Historical Financial Statement-"&'Data Sheet '!B2 -> Historical Financial Statement-RELIANCE INDUSTRIES LTD
B9: Year | C9: ='Data Sheet '!B17 -> 42825 | D9: ='Data Sheet '!C17 -> 43190 | E9: ='Data Sheet '!D17 -> 43555 | F9: ='Data Sheet '!E17 -> 43921 | G9: ='Data Sheet '!F17 -> 44286 | H9: ='Data Sheet '!G17 -> 44651 | I9: ='Data Sheet '!H17 -> 45016 | J9: ='Data Sheet '!I17 -> 45382 | ... L9: ='Data Sheet '!K17 -> 46112
A11: # | B11: Income Statement
B12: Sales | C12: =IFERROR('Data Sheet '!B18,0) -> 303954 | D12: =IFERROR('Data Sheet '!C18,0) -> 390823 | E12: =IFERROR('Data Sheet '!D18,0) -> 568337 | F12: =IFERROR('Data Sheet '!E18,0) -> 596679 | G12: =IFERROR('Data Sheet '!F18,0) -> 466307 | H12: =IFERROR('Data Sheet '!G18,0) -> 694673 | I12: =IFERROR('Data Sheet '!H18,0) -> 876396 | J12: =IFERROR('Data Sheet '!I18,0) -> 899041 | ... L12: =IFERROR('Data Sheet '!K18,0) -> 1055780
B13: Sales % Growth | D13: =D12/C12-1 -> 0.28579654 | E13: =E12/D12-1 -> 0.45420561 | F13: =F12/E12-1 -> 0.0498683 | G13: =G12/F12-1 -> -0.21849604 | H13: =H12/G12-1 -> 0.48973316 | I13: =I12/H12-1 -> 0.26159502 | J13: =J12/I12-1 -> 0.025838776 | K13: =K12/J12-1 -> 0.070941147 | L13: =L12/K12-1 -> 0.096549719
B15: ='Data Sheet '!A20 -> Change in Inventory | C15: ='Data Sheet '!B20 -> 5218 | D15: ='Data Sheet '!C20 -> 8610 | E15: ='Data Sheet '!D20 -> 4680 | F15: ='Data Sheet '!E20 -> 5048 | G15: ='Data Sheet '!F20 -> 9064 | H15: ='Data Sheet '!G20 -> 21457 | I15: ='Data Sheet '!H20 -> 30263 | ... L15: ='Data Sheet '!K20 -> 10267
B17: ='Data Sheet '!A19 -> Raw Material Cost | C17: =IFERROR('Data Sheet '!B19,0) -> 217518 | D17: =IFERROR('Data Sheet '!C19,0) -> 276076 | E17: =IFERROR('Data Sheet '!D19,0) -> 399167 | F17: =IFERROR('Data Sheet '!E19,0) -> 410288 | G17: =IFERROR('Data Sheet '!F19,0) -> 301765 | H17: =IFERROR('Data Sheet '!G19,0) -> 494449 | I17: =IFERROR('Data Sheet '!H19,0) -> 618746 | J17: =IFERROR('Data Sheet '!I19,0) -> 590226 | ... L17: =IFERROR('Data Sheet '!K19,0) -> 698930
B18: ='Data Sheet '!A21 -> Power and Fuel | C18: =IFERROR('Data Sheet '!B21,0) -> 11251 | D18: =IFERROR('Data Sheet '!C21,0) -> 14569 | E18: =IFERROR('Data Sheet '!D21,0) -> 17029 | F18: =IFERROR('Data Sheet '!E21,0) -> 15098 | G18: =IFERROR('Data Sheet '!F21,0) -> 13214 | H18: =IFERROR('Data Sheet '!G21,0) -> 17902 | I18: =IFERROR('Data Sheet '!H21,0) -> 25062 | J18: =IFERROR('Data Sheet '!I21,0) -> 22137 | ... L18: =IFERROR('Data Sheet '!K21,0) -> 22069
B19: ='Data Sheet '!A22 -> Other Mfr. Exp | C19: =IFERROR('Data Sheet '!B22,0) -> 9909 | D19: =IFERROR('Data Sheet '!C22,0) -> 9691 | E19: =IFERROR('Data Sheet '!D22,0) -> 12198 | F19: =IFERROR('Data Sheet '!E22,0) -> 11434 | G19: =IFERROR('Data Sheet '!F22,0) -> 7687 | H19: =IFERROR('Data Sheet '!G22,0) -> 12174 | I19: =IFERROR('Data Sheet '!H22,0) -> 19658 | J19: =IFERROR('Data Sheet '!I22,0) -> 18276 | ... L19: =IFERROR('Data Sheet '!K22,0) -> 21162
B20: ='Data Sheet '!A23 -> Employee Cost | C20: =IFERROR('Data Sheet '!B23,0) -> 8388 | D20: =IFERROR('Data Sheet '!C23,0) -> 9523 | E20: =IFERROR('Data Sheet '!D23,0) -> 12488 | F20: =IFERROR('Data Sheet '!E23,0) -> 14075 | G20: =IFERROR('Data Sheet '!F23,0) -> 14817 | H20: =IFERROR('Data Sheet '!G23,0) -> 18758 | I20: =IFERROR('Data Sheet '!H23,0) -> 24872 | J20: =IFERROR('Data Sheet '!I23,0) -> 25679 | ... L20: =IFERROR('Data Sheet '!K23,0) -> 30318
B22: COGS | C22: =IFERROR(SUM(C17,C18,C19,C20),0) -> 247066 | D22: =IFERROR(SUM(D17,D18,D19,D20),0) -> 309859 | E22: =IFERROR(SUM(E17,E18,E19,E20),0) -> 440882 | F22: =IFERROR(SUM(F17,F18,F19,F20),0) -> 450895 | G22: =IFERROR(SUM(G17,G18,G19,G20),0) -> 337483 | H22: =IFERROR(SUM(H17,H18,H19,H20),0) -> 543283 | I22: =IFERROR(SUM(I17,I18,I19,I20),0) -> 688338 | J22: =IFERROR(SUM(J17,J18,J19,J20),0) -> 656318 | ... L22: =IFERROR(SUM(L17,L18,L19,L20),0) -> 772479
B23: COGS % Sales | C23: =C22/C12 -> 0.8128401 | D23: =D22/D12 -> 0.79283717 | E23: =E22/E12 -> 0.77574045 | F23: =F22/F12 -> 0.75567432 | G23: =G22/G12 -> 0.72373565 | H23: =H22/H12 -> 0.78207013 | I23: =I22/I12 -> 0.78541892 | J23: =J22/J12 -> 0.7300201 | ... L23: =L22/L12 -> 0.73166664
B25: Gross Profit | C25: =IFERROR(SUM(C12,C15)-C22,0) -> 62106 | D25: =IFERROR(SUM(D12,D15)-D22,0) -> 89574 | E25: =IFERROR(SUM(E12,E15)-E22,0) -> 132135 | F25: =IFERROR(SUM(F12,F15)-F22,0) -> 150832 | G25: =IFERROR(SUM(G12,G15)-G22,0) -> 137888 | H25: =IFERROR(SUM(H12,H15)-H22,0) -> 172847 | I25: =IFERROR(SUM(I12,I15)-I22,0) -> 218321 | J25: =IFERROR(SUM(J12,J15)-J22,0) -> 247606 | ... L25: =IFERROR(SUM(L12,L15)-L22,0) -> 293568
B26: Gross Profit Margins | C26: =C25/C12 -> 0.20432697 | D26: =D25/D12 -> 0.22919327 | E26: =E25/E12 -> 0.2324941 | F26: =F25/F12 -> 0.25278584 | G26: =G25/G12 -> 0.29570219 | H26: =H25/H12 -> 0.24881779 | I26: =I25/I12 -> 0.24911227 | J26: =J25/J12 -> 0.27541124 | ... L26: =L25/L12 -> 0.27805793
B28: ='Data Sheet '!A24 -> Selling and admin | C28: ='Data Sheet '!B24 -> 18520 | D28: ='Data Sheet '!C24 -> 29111 | E28: ='Data Sheet '!D24 -> 50221 | F28: ='Data Sheet '!E24 -> 62622 | G28: ='Data Sheet '!F24 -> 56154 | H28: ='Data Sheet '!G24 -> 63513 | I28: ='Data Sheet '!H24 -> 67369 | ... L28: ='Data Sheet '!K24 -> 104723
B29: S&A Exp % Sales | C29: =C28/C12 -> 0.060930272 | D29: =D28/D12 -> 0.074486404 | E29: =E28/E12 -> 0.088364826 | F29: =F28/F12 -> 0.1049509 | G29: =G28/G12 -> 0.12042281 | H29: =H28/H12 -> 0.091428629 | I29: =I28/I12 -> 0.076870501 | J29: =J28/J12 -> 0.085971608 | ... L29: =L28/L12 -> 0.099190172
B31: ='Data Sheet '!A26 -> Other Income | C31: ='Data Sheet '!B26 -> 9222 | D31: ='Data Sheet '!C26 -> 9869 | E31: ='Data Sheet '!D26 -> 8406 | F31: ='Data Sheet '!E26 -> 8570 | G31: ='Data Sheet '!F26 -> 22432 | H31: ='Data Sheet '!G26 -> 19600 | I31: ='Data Sheet '!H26 -> 12020 | ... L31: ='Data Sheet '!K26 -> 28846
B32: Other income % Sales | C32: =C31/C12 -> 0.030340117 | D32: =D31/D12 -> 0.02525184 | E32: =E31/E12 -> 0.01479052 | F32: =F31/F12 -> 0.014362832 | G32: =G31/G12 -> 0.048105647 | H32: =H31/H12 -> 0.028214714 | I32: =I31/I12 -> 0.013715261 | J32: =J31/J12 -> 0.017565384 | ... L32: =L31/L12 -> 0.02732198
B34: ='Data Sheet '!A25 -> Other Expenses | C34: ='Data Sheet '!B25 -> -2721 | D34: ='Data Sheet '!C25 -> -3852 | E34: ='Data Sheet '!D25 -> -2336 | F34: ='Data Sheet '!E25 -> -1056 | G34: ='Data Sheet '!F25 -> 944 | H34: ='Data Sheet '!G25 -> 753 | I34: ='Data Sheet '!H25 -> 8634 | ... L34: ='Data Sheet '!K25 -> 9780
B35: Expense % Sales | C35: =C34/C12 -> -0.0089520125 | D35: =D34/D12 -> -0.0098561241 | E35: =E34/E12 -> -0.0041102374 | F35: =F34/F12 -> -0.0017697958 | G35: =G34/G12 -> 0.0020244174 | H35: =H34/H12 -> 0.0010839632 | I35: =I34/I12 -> 0.0098517109 | J35: =J34/J12 -> 0.0086937081 | ... L35: =L34/L12 -> 0.0092632935
B37: EBITDA | C37: =IFERROR(SUM(C25,C31)-C28-C34,0) -> 55529 | D37: =IFERROR(SUM(D25,D31)-D28-D34,0) -> 74184 | E37: =IFERROR(SUM(E25,E31)-E28-E34,0) -> 92656 | F37: =IFERROR(SUM(F25,F31)-F28-F34,0) -> 97836 | G37: =IFERROR(SUM(G25,G31)-G28-G34,0) -> 103222 | H37: =IFERROR(SUM(H25,H31)-H28-H34,0) -> 128181 | I37: =IFERROR(SUM(I25,I31)-I28-I34,0) -> 154338 | J37: =IFERROR(SUM(J25,J31)-J28-J34,0) -> 178290 | ... L37: =IFERROR(SUM(L25,L31)-L28-L34,0) -> 207911
B38: EBITDA % Margins | C38: =C37/C12 -> 0.18268883 | D38: =D37/D12 -> 0.18981483 | E38: =E37/E12 -> 0.16303003 | F38: =F37/F12 -> 0.16396756 | G38: =G37/G12 -> 0.22136061 | H38: =H37/H12 -> 0.18451991 | I38: =I37/I12 -> 0.17610532 | J38: =J37/J12 -> 0.19831131 | ... L38: =L37/L12 -> 0.19692644
B40: ='Data Sheet '!A27 -> Depreciation | C40: ='Data Sheet '!B27 -> 11646 | D40: ='Data Sheet '!C27 -> 16706 | E40: ='Data Sheet '!D27 -> 20934 | F40: ='Data Sheet '!E27 -> 22203 | G40: ='Data Sheet '!F27 -> 26572 | H40: ='Data Sheet '!G27 -> 29782 | I40: ='Data Sheet '!H27 -> 40303 | ... L40: ='Data Sheet '!K27 -> 57688
B41: Depreciation % Sales | C41: =C40/C12 -> 0.038315008 | D41: =D40/D12 -> 0.042745693 | E41: =E40/E12 -> 0.03683378 | F41: =F40/F12 -> 0.037210963 | G41: =G40/G12 -> 0.056983918 | H41: =H40/H12 -> 0.04287197 | I41: =I40/I12 -> 0.045987202 | J41: =J40/J12 -> 0.056540247 | ... L41: =L40/L12 -> 0.054640171
B43: ='Data Sheet '!A28 -> Interest | C43: ='Data Sheet '!B28 -> 3849 | D43: ='Data Sheet '!C28 -> 8052 | E43: ='Data Sheet '!D28 -> 16495 | F43: ='Data Sheet '!E28 -> 22027 | G43: ='Data Sheet '!F28 -> 21189 | H43: ='Data Sheet '!G28 -> 14584 | I43: ='Data Sheet '!H28 -> 19571 | ... L43: ='Data Sheet '!K28 -> 27061
B44: Interest % Sales | C44: =C43/C12 -> 0.0126631 | D44: =D43/D12 -> 0.020602677 | E44: =E43/E12 -> 0.029023273 | F44: =F43/F12 -> 0.036915997 | G44: =G43/G12 -> 0.045440021 | H44: =H43/H12 -> 0.02099405 | I44: =I43/I12 -> 0.022331229 | J44: =J43/J12 -> 0.025714066 | ... L44: =L43/L12 -> 0.025631287
B46: Earning Before Tax | C46: =IFERROR(C37-(SUM(C40,C43)),0) -> 40034 | D46: =IFERROR(D37-(SUM(D40,D43)),0) -> 49426 | E46: =IFERROR(E37-(SUM(E40,E43)),0) -> 55227 | F46: =IFERROR(F37-(SUM(F40,F43)),0) -> 53606 | G46: =IFERROR(G37-(SUM(G40,G43)),0) -> 55461 | H46: =IFERROR(H37-(SUM(H40,H43)),0) -> 83815 | I46: =IFERROR(I37-(SUM(I40,I43)),0) -> 94464 | J46: =IFERROR(J37-(SUM(J40,J43)),0) -> 104340 | ... L46: =IFERROR(L37-(SUM(L40,L43)),0) -> 123162
B47: EBT Margins | C47: =C46/C12 -> 0.13171072 | D47: =D46/D12 -> 0.12646646 | E47: =E46/E12 -> 0.09717298 | F47: =F46/F12 -> 0.089840601 | G47: =G46/G12 -> 0.11893667 | H47: =H46/H12 -> 0.12065389 | I47: =I46/I12 -> 0.10778689 | J47: =J46/J12 -> 0.116057 | ... L47: =L46/L12 -> 0.11665498
B49: ='Data Sheet '!A30 -> Tax | C49: =IFERROR('Data Sheet '!B30,0) -> 10201 | D49: =IFERROR('Data Sheet '!C30,0) -> 13346 | E49: =IFERROR('Data Sheet '!D30,0) -> 15390 | F49: =IFERROR('Data Sheet '!E30,0) -> 13726 | G49: =IFERROR('Data Sheet '!F30,0) -> 1722 | H49: =IFERROR('Data Sheet '!G30,0) -> 15970 | I49: =IFERROR('Data Sheet '!H30,0) -> 20376 | J49: =IFERROR('Data Sheet '!I30,0) -> 25707 | ... L49: =IFERROR('Data Sheet '!K30,0) -> 27552
B50: Effective Tax Rate | C50: =C49/C46 -> 0.25480841 | D50: =D49/D46 -> 0.27001983 | E50: =E49/E46 -> 0.27866804 | F50: =F49/F46 -> 0.25605343 | G50: =G49/G46 -> 0.031048845 | H50: =H49/H46 -> 0.19053869 | I50: =I49/I46 -> 0.21570122 | J50: =J49/J46 -> 0.24637723 | ... L50: =L49/L46 -> 0.22370536
B52: Net Profit | C52: =IFERROR(C46-C49,0) -> 29833 | D52: =IFERROR(D46-D49,0) -> 36080 | E52: =IFERROR(E46-E49,0) -> 39837 | F52: =IFERROR(F46-F49,0) -> 39880 | G52: =IFERROR(G46-G49,0) -> 53739 | H52: =IFERROR(H46-H49,0) -> 67845 | I52: =IFERROR(I46-I49,0) -> 74088 | J52: =IFERROR(J46-J49,0) -> 78633 | ... L52: =IFERROR(L46-L49,0) -> 95610
B53: Net Margin | C53: =C52/C12 -> 0.09814972 | D53: =D52/D12 -> 0.092318006 | E53: =E52/E12 -> 0.070093976 | F53: =F52/F12 -> 0.066836607 | G53: =G52/G12 -> 0.11524382 | H53: =H52/H12 -> 0.097664657 | I53: =I52/I12 -> 0.084537127 | J53: =J52/J12 -> 0.087463197 | ... L53: =L52/L12 -> 0.090558639
B55: No of equity Shares | C55: =IFERROR('Data Sheet '!B94,0) -> 1387.22 | D55: =IFERROR('Data Sheet '!C94,0) -> 1351.39 | E55: =IFERROR('Data Sheet '!D94,0) -> 1352.26 | F55: =IFERROR('Data Sheet '!E94,0) -> 1352.37 | G55: =IFERROR('Data Sheet '!F94,0) -> 1267.89 | H55: =IFERROR('Data Sheet '!G94,0) -> 1352.98 | I55: =IFERROR('Data Sheet '!H94,0) -> 1353.12 | J55: =IFERROR('Data Sheet '!I94,0) -> 1353.14 | ... L55: =IFERROR('Data Sheet '!K94,0) -> 1353.25
B57: Earnings per Share | C57: =C52/C55 -> 21.505601 | D57: =D52/D55 -> 26.698436 | E57: =E52/E55 -> 29.459571 | F57: =F52/F55 -> 29.488971 | G57: =G52/G55 -> 42.384592 | H57: =H52/H55 -> 50.144865 | I57: =I52/I55 -> 54.753459 | J57: =J52/J55 -> 58.111504 | ... L57: =L52/L55 -> 70.652134
B58: EPS Growth | D58: =D57/C57-1 -> 0.24146432 | E58: =E57/D57-1 -> 0.10341935 | F58: =F57/E57-1 -> 0.00099797207 | G58: =G57/F57-1 -> 0.43730317 | H58: =H57/G57-1 -> 0.18309186 | I58: =I57/H57-1 -> 0.091905586 | J58: =J57/I57-1 -> 0.06133028 | K58: =K57/J57-1 -> 0.027317158 | L58: =L57/K57-1 -> 0.18347375
B60: Dividend Per Share | C60: =IFERROR(C63/C55,0) -> 2.3463474 | D60: =IFERROR(D63/D55,0) -> 2.6292928 | E60: =IFERROR(E63/E55,0) -> 2.8484907 | F60: =IFERROR(F63/F55,0) -> 3.0467624 | G60: =IFERROR(G63/G55,0) -> 3.558274 | H60: =IFERROR(H63/H55,0) -> 4.0000591 | I60: =IFERROR(I63/I55,0) -> 4.5002661 | J60: =IFERROR(J63/J55,0) -> 5.0002217 | ... L60: =IFERROR(L63/L55,0) -> 5.9997783
B61: Dividend Payout Ratio | C61: =C60/C57 -> 0.10910401 | D61: =D60/D57 -> 0.098481153 | E61: =E60/E57 -> 0.096691518 | F61: =F60/F57 -> 0.10331871 | G61: =G60/G57 -> 0.083952065 | H61: =H60/H57 -> 0.079770064 | I61: =I60/I57 -> 0.082191448 | J61: =J60/J57 -> 0.086045299 | ... L61: =L60/L57 -> 0.084919987
B63: Divident Amount | C63: =IFERROR('Data Sheet '!B32,0) -> 3254.9 | D63: =IFERROR('Data Sheet '!C32,0) -> 3553.2 | E63: =IFERROR('Data Sheet '!D32,0) -> 3851.9 | F63: =IFERROR('Data Sheet '!E32,0) -> 4120.35 | G63: =IFERROR('Data Sheet '!F32,0) -> 4511.5 | H63: =IFERROR('Data Sheet '!G32,0) -> 5412 | I63: =IFERROR('Data Sheet '!H32,0) -> 6089.4 | J63: =IFERROR('Data Sheet '!I32,0) -> 6766 | ... L63: =IFERROR('Data Sheet '!K32,0) -> 8119.2
B65: Retained Earnings | C65: =IFERROR(IF(C57>C60,1-C61,0),0) -> 0.89089599 | D65: =IFERROR(IF(D57>D60,1-D61,0),0) -> 0.90151885 | E65: =IFERROR(IF(E57>E60,1-E61,0),0) -> 0.90330848 | F65: =IFERROR(IF(F57>F60,1-F61,0),0) -> 0.89668129 | G65: =IFERROR(IF(G57>G60,1-G61,0),0) -> 0.91604794 | H65: =IFERROR(IF(H57>H60,1-H61,0),0) -> 0.92022994 | I65: =IFERROR(IF(I57>I60,1-I61,0),0) -> 0.91780855 | J65: =IFERROR(IF(J57>J60,1-J61,0),0) -> 0.9139547 | ... L65: =IFERROR(IF(L57>L60,1-L61,0),0) -> 0.91508001
A67: # | B67: Balance Sheet
B68: Equity Share Capital | C68: =IFERROR('Data Sheet '!B58,0) -> 2959 | D68: =IFERROR('Data Sheet '!C58,0) -> 5922 | E68: =IFERROR('Data Sheet '!D58,0) -> 5926 | F68: =IFERROR('Data Sheet '!E58,0) -> 6339 | G68: =IFERROR('Data Sheet '!F58,0) -> 6445 | H68: =IFERROR('Data Sheet '!G58,0) -> 6765 | I68: =IFERROR('Data Sheet '!H58,0) -> 6766 | J68: =IFERROR('Data Sheet '!I58,0) -> 6766 | ... L68: =IFERROR('Data Sheet '!K58,0) -> 13532
B69: Reserves | C69: =IFERROR('Data Sheet '!B59,0) -> 260750 | D69: =IFERROR('Data Sheet '!C59,0) -> 287584 | E69: =IFERROR('Data Sheet '!D59,0) -> 381186 | F69: =IFERROR('Data Sheet '!E59,0) -> 442827 | G69: =IFERROR('Data Sheet '!F59,0) -> 693727 | H69: =IFERROR('Data Sheet '!G59,0) -> 772720 | I69: =IFERROR('Data Sheet '!H59,0) -> 709106 | J69: =IFERROR('Data Sheet '!I59,0) -> 786715 | ... L69: =IFERROR('Data Sheet '!K59,0) -> 890498
B70: Borrowings | C70: =IFERROR('Data Sheet '!B60,0) -> 217475 | D70: =IFERROR('Data Sheet '!C60,0) -> 239843 | E70: =IFERROR('Data Sheet '!D60,0) -> 307714 | F70: =IFERROR('Data Sheet '!E60,0) -> 355133 | G70: =IFERROR('Data Sheet '!F60,0) -> 278962 | H70: =IFERROR('Data Sheet '!G60,0) -> 319158 | I70: =IFERROR('Data Sheet '!H60,0) -> 451664 | J70: =IFERROR('Data Sheet '!I60,0) -> 350719 | ... L70: =IFERROR('Data Sheet '!K60,0) -> 402962
B71: Other Liabilities | C71: =IFERROR('Data Sheet '!B61,0) -> 225618 | D71: =IFERROR('Data Sheet '!C61,0) -> 277924 | E71: =IFERROR('Data Sheet '!D61,0) -> 302804 | F71: =IFERROR('Data Sheet '!E61,0) -> 358716 | G71: =IFERROR('Data Sheet '!F61,0) -> 340931 | H71: =IFERROR('Data Sheet '!G61,0) -> 399979 | I71: =IFERROR('Data Sheet '!H61,0) -> 438346 | J71: =IFERROR('Data Sheet '!I61,0) -> 610848 | ... L71: =IFERROR('Data Sheet '!K61,0) -> 870554
B72: Total Liabilities | C72: =SUM(C68:C71) -> 706802 | D72: =SUM(D68:D71) -> 811273 | E72: =SUM(E68:E71) -> 997630 | F72: =SUM(F68:F71) -> 1163015 | G72: =SUM(G68:G71) -> 1320065 | H72: =SUM(H68:H71) -> 1498622 | I72: =SUM(I68:I71) -> 1605882 | J72: =SUM(J68:J71) -> 1755048 | ... L72: =SUM(L68:L71) -> 2177546
B74: Fixed asset Net Block | C74: =IFERROR('Data Sheet '!B63,0) -> 198526 | D74: =IFERROR('Data Sheet '!C63,0) -> 403885 | E74: =IFERROR('Data Sheet '!D63,0) -> 398374 | F74: =IFERROR('Data Sheet '!E63,0) -> 532658 | G74: =IFERROR('Data Sheet '!F63,0) -> 541258 | H74: =IFERROR('Data Sheet '!G63,0) -> 627798 | I74: =IFERROR('Data Sheet '!H63,0) -> 724805 | J74: =IFERROR('Data Sheet '!I63,0) -> 779985 | ... L74: =IFERROR('Data Sheet '!K63,0) -> 1124795
B75: CWIP | C75: =IFERROR('Data Sheet '!B64,0) -> 324837 | D75: =IFERROR('Data Sheet '!C64,0) -> 187022 | E75: =IFERROR('Data Sheet '!D64,0) -> 179463 | F75: =IFERROR('Data Sheet '!E64,0) -> 109106 | G75: =IFERROR('Data Sheet '!F64,0) -> 125953 | H75: =IFERROR('Data Sheet '!G64,0) -> 172506 | I75: =IFERROR('Data Sheet '!H64,0) -> 293752 | J75: =IFERROR('Data Sheet '!I64,0) -> 338855 | ... L75: =IFERROR('Data Sheet '!K64,0) -> 237686
B76: Investments | C76: =IFERROR('Data Sheet '!B65,0) -> 82899 | D76: =IFERROR('Data Sheet '!C65,0) -> 82862 | E76: =IFERROR('Data Sheet '!D65,0) -> 235635 | F76: =IFERROR('Data Sheet '!E65,0) -> 276767 | G76: =IFERROR('Data Sheet '!F65,0) -> 364828 | H76: =IFERROR('Data Sheet '!G65,0) -> 394264 | I76: =IFERROR('Data Sheet '!H65,0) -> 235560 | J76: =IFERROR('Data Sheet '!I65,0) -> 225672 | ... L76: =IFERROR('Data Sheet '!K65,0) -> 248332
B77: Other assets | C77: =IFERROR('Data Sheet '!B66-SUM('Data Sheet '!B68:B70),0) -> 40389 | D77: =IFERROR('Data Sheet '!C66-SUM('Data Sheet '!C68:C70),0) -> 54857 | E77: =IFERROR('Data Sheet '!D66-SUM('Data Sheet '!D68:D70),0) -> 75427 | F77: =IFERROR('Data Sheet '!E66-SUM('Data Sheet '!E68:E70),0) -> 120005 | G77: =IFERROR('Data Sheet '!F66-SUM('Data Sheet '!F68:F70),0) -> 169943 | H77: =IFERROR('Data Sheet '!G66-SUM('Data Sheet '!G68:G70),0) -> 136458 | I77: =IFERROR('Data Sheet '!H66-SUM('Data Sheet '!H68:H70),0) -> 114645 | J77: =IFERROR('Data Sheet '!I66-SUM('Data Sheet '!I68:I70),0) -> 128913 | ... L77: =IFERROR('Data Sheet '!K66-SUM('Data Sheet '!K68:K70),0) -> 195324
B78: Total Non Current Assets | C78: =SUM(C74:C77) -> 646651 | D78: =SUM(D74:D77) -> 728626 | E78: =SUM(E74:E77) -> 888899 | F78: =SUM(F74:F77) -> 1038536 | G78: =SUM(G74:G77) -> 1201982 | H78: =SUM(H74:H77) -> 1331026 | I78: =SUM(I74:I77) -> 1368762 | J78: =SUM(J74:J77) -> 1473425 | ... L78: =SUM(L74:L77) -> 1806137
B80: Receivables | C80: =IFERROR('Data Sheet '!B68,0) -> 8177 | D80: =IFERROR('Data Sheet '!C68,0) -> 17555 | E80: =IFERROR('Data Sheet '!D68,0) -> 30089 | F80: =IFERROR('Data Sheet '!E68,0) -> 19656 | G80: =IFERROR('Data Sheet '!F68,0) -> 19014 | H80: =IFERROR('Data Sheet '!G68,0) -> 23640 | I80: =IFERROR('Data Sheet '!H68,0) -> 28448 | J80: =IFERROR('Data Sheet '!I68,0) -> 31628 | ... L80: =IFERROR('Data Sheet '!K68,0) -> 58491
B81: Inventory | C81: =IFERROR('Data Sheet '!B69,0) -> 48951 | D81: =IFERROR('Data Sheet '!C69,0) -> 60837 | E81: =IFERROR('Data Sheet '!D69,0) -> 67561 | F81: =IFERROR('Data Sheet '!E69,0) -> 73903 | G81: =IFERROR('Data Sheet '!F69,0) -> 81672 | H81: =IFERROR('Data Sheet '!G69,0) -> 107778 | I81: =IFERROR('Data Sheet '!H69,0) -> 140008 | J81: =IFERROR('Data Sheet '!I69,0) -> 152770 | ... L81: =IFERROR('Data Sheet '!K69,0) -> 166941
B82: Cash and Bank | C82: =IFERROR('Data Sheet '!B70,0) -> 3023 | D82: =IFERROR('Data Sheet '!C70,0) -> 4255 | E82: =IFERROR('Data Sheet '!D70,0) -> 11081 | F82: =IFERROR('Data Sheet '!E70,0) -> 30920 | G82: =IFERROR('Data Sheet '!F70,0) -> 17397 | H82: =IFERROR('Data Sheet '!G70,0) -> 36178 | I82: =IFERROR('Data Sheet '!H70,0) -> 68664 | J82: =IFERROR('Data Sheet '!I70,0) -> 97225 | ... L82: =IFERROR('Data Sheet '!K70,0) -> 145977
B83: Total Current Assets | C83: =SUM(C80:C82) -> 60151 | D83: =SUM(D80:D82) -> 82647 | E83: =SUM(E80:E82) -> 108731 | F83: =SUM(F80:F82) -> 124479 | G83: =SUM(G80:G82) -> 118083 | H83: =SUM(H80:H82) -> 167596 | I83: =SUM(I80:I82) -> 237120 | J83: =SUM(J80:J82) -> 281623 | ... L83: =SUM(L80:L82) -> 371409
B85: Total Assets | C85: =SUM(C78,C83) -> 706802 | D85: =SUM(D78,D83) -> 811273 | E85: =SUM(E78,E83) -> 997630 | F85: =SUM(F78,F83) -> 1163015 | G85: =SUM(G78,G83) -> 1320065 | H85: =SUM(H78,H83) -> 1498622 | I85: =SUM(I78,I83) -> 1605882 | J85: =SUM(J78,J83) -> 1755048 | ... L85: =SUM(L78,L83) -> 2177546
B87: Check | C87: =C85=C72 -> TRUE | D87: =D85=D72 -> TRUE | E87: =E85=E72 -> TRUE | F87: =F85=F72 -> TRUE | G87: =G85=G72 -> TRUE | H87: =H85=H72 -> TRUE | I87: =I85=I72 -> TRUE | J87: =J85=J72 -> TRUE | ... L87: =L85=L72 -> TRUE
A89: # | B89: Cash Flow Statements
B90: Cash From Operating Activities | C90: =IFERROR('Data Sheet '!B83,0) -> 49550 | D90: =IFERROR('Data Sheet '!C83,0) -> 71459 | E90: =IFERROR('Data Sheet '!D83,0) -> 42346 | F90: =IFERROR('Data Sheet '!E83,0) -> 94877 | G90: =IFERROR('Data Sheet '!F83,0) -> 26958 | H90: =IFERROR('Data Sheet '!G83,0) -> 110654 | I90: =IFERROR('Data Sheet '!H83,0) -> 115032 | J90: =IFERROR('Data Sheet '!I83,0) -> 158788 | ... L90: =IFERROR('Data Sheet '!K83,0) -> 192113
B92: Cash From Investing Activities | C92: =IFERROR('Data Sheet '!B84,0) -> -66201 | D92: =IFERROR('Data Sheet '!C84,0) -> -68192 | E92: =IFERROR('Data Sheet '!D84,0) -> -94507 | F92: =IFERROR('Data Sheet '!E84,0) -> -72497 | G92: =IFERROR('Data Sheet '!F84,0) -> -142385 | H92: =IFERROR('Data Sheet '!G84,0) -> -109162 | I92: =IFERROR('Data Sheet '!H84,0) -> -93001 | J92: =IFERROR('Data Sheet '!I84,0) -> -113581 | ... L92: =IFERROR('Data Sheet '!K84,0) -> -101089
B94: Cash From Financing Activities | C94: =IFERROR('Data Sheet '!B85,0) -> 8617 | D94: =IFERROR('Data Sheet '!C85,0) -> -2001 | E94: =IFERROR('Data Sheet '!D85,0) -> 55906 | F94: =IFERROR('Data Sheet '!E85,0) -> -2541 | G94: =IFERROR('Data Sheet '!F85,0) -> 101904 | H94: =IFERROR('Data Sheet '!G85,0) -> 17289 | I94: =IFERROR('Data Sheet '!H85,0) -> 10455 | J94: =IFERROR('Data Sheet '!I85,0) -> -16646 | ... L94: =IFERROR('Data Sheet '!K85,0) -> -51549
B96: Net Cash flow | C96: =SUM(C90:C94) -> -8034 | D96: =SUM(D90:D94) -> 1266 | E96: =SUM(E90:E94) -> 3745 | F96: =SUM(F90:F94) -> 19839 | G96: =SUM(G90:G94) -> -13523 | H96: =SUM(H90:H94) -> 18781 | I96: =SUM(I90:I94) -> 32486 | J96: =SUM(J90:J94) -> 28561 | ... L96: =SUM(L90:L94) -> 39475

Sheet Ratio Analysis
B8: ="RATIO ANALYSIS-"&'Data Sheet '!B2 -> RATIO ANALYSIS-RELIANCE INDUSTRIES LTD
B9: Year | C9: ='Data Sheet '!B17 -> 42825 | D9: ='Data Sheet '!C17 -> 43190 | E9: ='Data Sheet '!D17 -> 43555 | F9: ='Data Sheet '!E17 -> 43921 | G9: ='Data Sheet '!F17 -> 44286 | H9: ='Data Sheet '!G17 -> 44651 | I9: ='Data Sheet '!H17 -> 45016 | J9: ='Data Sheet '!I17 -> 45382 | ... L9: ='Data Sheet '!K17 -> 46112 | M9: Trend Line | N9: Mean | O9: Median
B11: Sales Growth | D11: =IFERROR(HistoricalFS!D13,0) -> 0.28579654 | E11: =IFERROR(HistoricalFS!E13,0) -> 0.45420561 | F11: =IFERROR(HistoricalFS!F13,0) -> 0.0498683 | G11: =IFERROR(HistoricalFS!G13,0) -> -0.21849604 | H11: =IFERROR(HistoricalFS!H13,0) -> 0.48973316 | I11: =IFERROR(HistoricalFS!I13,0) -> 0.26159502 | J11: =IFERROR(HistoricalFS!J13,0) -> 0.025838776 | K11: =IFERROR(HistoricalFS!K13,0) -> 0.070941147 | L11: =IFERROR(HistoricalFS!L13,0) -> 0.096549719 | N11: =AVERAGE(D11:L11) -> 0.16844803 | O11: =MEDIAN(D11:L11) -> 0.096549719
B12: EBITDA Growth | D12: =IFERROR(HistoricalFS!D37/HistoricalFS!C37-1,0) -> 0.33595058 | E12: =IFERROR(HistoricalFS!E37/HistoricalFS!D37-1,0) -> 0.24900248 | F12: =IFERROR(HistoricalFS!F37/HistoricalFS!E37-1,0) -> 0.055905716 | G12: =IFERROR(HistoricalFS!G37/HistoricalFS!F37-1,0) -> 0.05505131 | H12: =IFERROR(HistoricalFS!H37/HistoricalFS!G37-1,0) -> 0.24179923 | I12: =IFERROR(HistoricalFS!I37/HistoricalFS!H37-1,0) -> 0.204063 | J12: =IFERROR(HistoricalFS!J37/HistoricalFS!I37-1,0) -> 0.15519185 | K12: =IFERROR(HistoricalFS!K37/HistoricalFS!J37-1,0) -> 0.028784564 | L12: =IFERROR(HistoricalFS!L37/HistoricalFS!K37-1,0) -> 0.13351179 | N12: =AVERAGE(D12:L12) -> 0.16214006 | O12: =MEDIAN(D12:L12) -> 0.15519185
B13: EBIT Growth | D13: =IFERROR(HistoricalFS!D46/HistoricalFS!C46-1,0) -> 0.23460059 | E13: =IFERROR(HistoricalFS!E46/HistoricalFS!D46-1,0) -> 0.11736738 | F13: =IFERROR(HistoricalFS!F46/HistoricalFS!E46-1,0) -> -0.029351585 | G13: =IFERROR(HistoricalFS!G46/HistoricalFS!F46-1,0) -> 0.034604335 | H13: =IFERROR(HistoricalFS!H46/HistoricalFS!G46-1,0) -> 0.51124213 | I13: =IFERROR(HistoricalFS!I46/HistoricalFS!H46-1,0) -> 0.12705363 | J13: =IFERROR(HistoricalFS!J46/HistoricalFS!I46-1,0) -> 0.10454776 | K13: =IFERROR(HistoricalFS!K46/HistoricalFS!J46-1,0) -> 0.016072455 | L13: =IFERROR(HistoricalFS!L46/HistoricalFS!K46-1,0) -> 0.16171935 | N13: =AVERAGE(D13:L13) -> 0.14198401 | O13: =MEDIAN(D13:L13) -> 0.11736738
B14: Net Profit Growth | D14: =IFERROR(HistoricalFS!D52/HistoricalFS!C52-1,0) -> 0.20939899 | E14: =IFERROR(HistoricalFS!E52/HistoricalFS!D52-1,0) -> 0.10412971 | F14: =IFERROR(HistoricalFS!F52/HistoricalFS!E52-1,0) -> 0.0010793985 | G14: =IFERROR(HistoricalFS!G52/HistoricalFS!F52-1,0) -> 0.34751755 | H14: =IFERROR(HistoricalFS!H52/HistoricalFS!G52-1,0) -> 0.26249093 | I14: =IFERROR(HistoricalFS!I52/HistoricalFS!H52-1,0) -> 0.092018572 | J14: =IFERROR(HistoricalFS!J52/HistoricalFS!I52-1,0) -> 0.061345967 | K14: =IFERROR(HistoricalFS!K52/HistoricalFS!J52-1,0) -> 0.027393079 | L14: =IFERROR(HistoricalFS!L52/HistoricalFS!K52-1,0) -> 0.18348249 | N14: =AVERAGE(D14:L14) -> 0.1432063 | O14: =MEDIAN(D14:L14) -> 0.10412971
B15: Dividend Growth | D15: =IFERROR(HistoricalFS!D63/HistoricalFS!C63-1,0) -> 0.091646441 | E15: =IFERROR(HistoricalFS!E63/HistoricalFS!D63-1,0) -> 0.084065068 | F15: =IFERROR(HistoricalFS!F63/HistoricalFS!E63-1,0) -> 0.069692879 | G15: =IFERROR(HistoricalFS!G63/HistoricalFS!F63-1,0) -> 0.094931256 | H15: =IFERROR(HistoricalFS!H63/HistoricalFS!G63-1,0) -> 0.19960102 | I15: =IFERROR(HistoricalFS!I63/HistoricalFS!H63-1,0) -> 0.1251663 | J15: =IFERROR(HistoricalFS!J63/HistoricalFS!I63-1,0) -> 0.11111111 | K15: =IFERROR(HistoricalFS!K63/HistoricalFS!J63-1,0) -> 0.1 | L15: =IFERROR(HistoricalFS!L63/HistoricalFS!K63-1,0) -> 0.090909091 | N15: =AVERAGE(D15:L15) -> 0.10745813 | O15: =MEDIAN(D15:L15) -> 0.094931256
B17: Gross Margin | C17: =HistoricalFS!C26 -> 0.20432697 | D17: =HistoricalFS!D26 -> 0.22919327 | E17: =HistoricalFS!E26 -> 0.2324941 | F17: =HistoricalFS!F26 -> 0.25278584 | G17: =HistoricalFS!G26 -> 0.29570219 | H17: =HistoricalFS!H26 -> 0.24881779 | I17: =HistoricalFS!I26 -> 0.24911227 | J17: =HistoricalFS!J26 -> 0.27541124 | ... L17: =HistoricalFS!L26 -> 0.27805793 | N17: =AVERAGE(C17:L17) -> 0.2538425 | O17: =MEDIAN(C17:L17) -> 0.25094905
B18: EBITDA Margin | C18: =HistoricalFS!C38 -> 0.18268883 | D18: =HistoricalFS!D38 -> 0.18981483 | E18: =HistoricalFS!E38 -> 0.16303003 | F18: =HistoricalFS!F38 -> 0.16396756 | G18: =HistoricalFS!G38 -> 0.22136061 | H18: =HistoricalFS!H38 -> 0.18451991 | I18: =HistoricalFS!I38 -> 0.17610532 | J18: =HistoricalFS!J38 -> 0.19831131 | ... L18: =HistoricalFS!L38 -> 0.19692644 | N18: =AVERAGE(C18:L18) -> 0.18672298 | O18: =MEDIAN(C18:L18) -> 0.18716737
B19: EBT Margin | C19: =HistoricalFS!C47 -> 0.13171072 | D19: =HistoricalFS!D47 -> 0.12646646 | E19: =HistoricalFS!E47 -> 0.09717298 | F19: =HistoricalFS!F47 -> 0.089840601 | G19: =HistoricalFS!G47 -> 0.11893667 | H19: =HistoricalFS!H47 -> 0.12065389 | I19: =HistoricalFS!I47 -> 0.10778689 | J19: =HistoricalFS!J47 -> 0.116057 | ... L19: =HistoricalFS!L47 -> 0.11665498 | N19: =AVERAGE(C19:L19) -> 0.11353911 | O19: =MEDIAN(C19:L19) -> 0.11635599
B20: Net Profit Margin | C20: =HistoricalFS!C53 -> 0.09814972 | D20: =HistoricalFS!D53 -> 0.092318006 | E20: =HistoricalFS!E53 -> 0.070093976 | F20: =HistoricalFS!F53 -> 0.066836607 | G20: =HistoricalFS!G53 -> 0.11524382 | H20: =HistoricalFS!H53 -> 0.097664657 | I20: =HistoricalFS!I53 -> 0.084537127 | J20: =HistoricalFS!J53 -> 0.087463197 | ... L20: =HistoricalFS!L53 -> 0.090558639 | N20: =AVERAGE(C20:L20) -> 0.08867724 | O20: =MEDIAN(C20:L20) -> 0.089010918
B22: Selling Expenses % Sales | C22: =HistoricalFS!C29 -> 0.060930272 | D22: =HistoricalFS!D29 -> 0.074486404 | E22: =HistoricalFS!E29 -> 0.088364826 | F22: =HistoricalFS!F29 -> 0.1049509 | G22: =HistoricalFS!G29 -> 0.12042281 | H22: =HistoricalFS!H29 -> 0.091428629 | I22: =HistoricalFS!I29 -> 0.076870501 | J22: =HistoricalFS!J29 -> 0.085971608 | ... L22: =HistoricalFS!L29 -> 0.099190172 | N22: =AVERAGE(C22:L22) -> 0.089480366 | O22: =MEDIAN(C22:L22) -> 0.089896727
B23: Depreciation % Sales | C23: =HistoricalFS!C41 -> 0.038315008 | D23: =HistoricalFS!D41 -> 0.042745693 | E23: =HistoricalFS!E41 -> 0.03683378 | F23: =HistoricalFS!F41 -> 0.037210963 | G23: =HistoricalFS!G41 -> 0.056983918 | H23: =HistoricalFS!H41 -> 0.04287197 | I23: =HistoricalFS!I41 -> 0.045987202 | J23: =HistoricalFS!J41 -> 0.056540247 | ... L23: =HistoricalFS!L41 -> 0.054640171 | N23: =AVERAGE(C23:L23) -> 0.046731684 | O23: =MEDIAN(C23:L23) -> 0.044429586
B24: Operating Income % Sales | C24: =(HistoricalFS!C37-HistoricalFS!C40)/HistoricalFS!C12 -> 0.14437382 | D24: =(HistoricalFS!D37-HistoricalFS!D40)/HistoricalFS!D12 -> 0.14706913 | E24: =(HistoricalFS!E37-HistoricalFS!E40)/HistoricalFS!E12 -> 0.12619625 | F24: =(HistoricalFS!F37-HistoricalFS!F40)/HistoricalFS!F12 -> 0.1267566 | G24: =(HistoricalFS!G37-HistoricalFS!G40)/HistoricalFS!G12 -> 0.16437669 | H24: =(HistoricalFS!H37-HistoricalFS!H40)/HistoricalFS!H12 -> 0.14164794 | I24: =(HistoricalFS!I37-HistoricalFS!I40)/HistoricalFS!I12 -> 0.13011812 | J24: =(HistoricalFS!J37-HistoricalFS!J40)/HistoricalFS!J12 -> 0.14177106 | ... L24: =(HistoricalFS!L37-HistoricalFS!L40)/HistoricalFS!L12 -> 0.14228627 | N24: =AVERAGE(C24:L24) -> 0.1399913 | O24: =MEDIAN(C24:L24) -> 0.1417095
B26: Return on Capital Employed | C26: =(HistoricalFS!C37-HistoricalFS!C40)/SUM(HistoricalFS!C68:C70) -> 0.091197962 | D26: =(HistoricalFS!D37-HistoricalFS!D40)/SUM(HistoricalFS!D68:D70) -> 0.10776808 | E26: =(HistoricalFS!E37-HistoricalFS!E40)/SUM(HistoricalFS!E68:E70) -> 0.10322297 | F26: =(HistoricalFS!F37-HistoricalFS!F40)/SUM(HistoricalFS!F68:F70) -> 0.094035924 | G26: =(HistoricalFS!G37-HistoricalFS!G40)/SUM(HistoricalFS!G68:G70) -> 0.078283463 | H26: =(HistoricalFS!H37-HistoricalFS!H40)/SUM(HistoricalFS!H68:H70) -> 0.089564126 | I26: =(HistoricalFS!I37-HistoricalFS!I40)/SUM(HistoricalFS!I68:I70) -> 0.097671506 | J26: =(HistoricalFS!J37-HistoricalFS!J40)/SUM(HistoricalFS!J68:J70) -> 0.11139486 | ... L26: =(HistoricalFS!L37-HistoricalFS!L40)/SUM(HistoricalFS!L68:L70) -> 0.11493796 | N26: =AVERAGE(C26:L26) -> 0.09950868 | O26: =MEDIAN(C26:L26) -> 0.10044724
B27: Retained Earnings | C27: =HistoricalFS!C65 -> 0.89089599 | D27: =HistoricalFS!D65 -> 0.90151885 | E27: =HistoricalFS!E65 -> 0.90330848 | F27: =HistoricalFS!F65 -> 0.89668129 | G27: =HistoricalFS!G65 -> 0.91604794 | H27: =HistoricalFS!H65 -> 0.92022994 | I27: =HistoricalFS!I65 -> 0.91780855 | J27: =HistoricalFS!J65 -> 0.9139547 | ... L27: =HistoricalFS!L65 -> 0.91508001 | N27: =AVERAGE(C27:L27) -> 0.90833995 | O27: =MEDIAN(C27:L27) -> 0.91091425
B28: Return on Equity | C28: =HistoricalFS!C52/SUM(HistoricalFS!C68:C69) -> 0.11312849 | D28: =HistoricalFS!D52/SUM(HistoricalFS!D68:D69) -> 0.12292764 | E28: =HistoricalFS!E52/SUM(HistoricalFS!E68:E69) -> 0.1029082 | F28: =HistoricalFS!F52/SUM(HistoricalFS!F68:F69) -> 0.088786774 | G28: =HistoricalFS!G52/SUM(HistoricalFS!G68:G69) -> 0.076751141 | H28: =HistoricalFS!H52/SUM(HistoricalFS!H68:H69) -> 0.087038237 | I28: =HistoricalFS!I52/SUM(HistoricalFS!I68:I69) -> 0.10349336 | J28: =HistoricalFS!J52/SUM(HistoricalFS!J68:J69) -> 0.099098781 | ... L28: =HistoricalFS!L52/SUM(HistoricalFS!L68:L69) -> 0.10575976 | N28: =AVERAGE(C28:L28) -> 0.09957024 | O28: =MEDIAN(C28:L28) -> 0.10100349
B29: Self Sustained Growth Rate | C29: =C27*C28 -> 0.10078571 | D29: =D27*D28 -> 0.11082158 | E29: =E27*E28 -> 0.092957852 | F29: =F27*F28 -> 0.079613439 | G29: =G27*G28 -> 0.070307724 | H29: =H27*H28 -> 0.080095191 | I29: =I27*I28 -> 0.094987093 | J29: =J27*J28 -> 0.090571797 | ... L29: =L27*L28 -> 0.096778647 | N29: =AVERAGE(C29:L29) -> 0.090390244 | O29: =MEDIAN(C29:L29) -> 0.091764824
B30: Interest Coverage Ratio | C30: =(HistoricalFS!C37-HistoricalFS!C40)/HistoricalFS!C43 -> 11.401143 | D30: =(HistoricalFS!D37-HistoricalFS!D40)/HistoricalFS!D43 -> 7.1383507 | E30: =(HistoricalFS!E37-HistoricalFS!E40)/HistoricalFS!E43 -> 4.3481055 | F30: =(HistoricalFS!F37-HistoricalFS!F40)/HistoricalFS!F43 -> 3.4336496 | G30: =(HistoricalFS!G37-HistoricalFS!G40)/HistoricalFS!G43 -> 3.617443 | H30: =(HistoricalFS!H37-HistoricalFS!H40)/HistoricalFS!H43 -> 6.7470516 | I30: =(HistoricalFS!I37-HistoricalFS!I40)/HistoricalFS!I43 -> 5.8267334 | J30: =(HistoricalFS!J37-HistoricalFS!J40)/HistoricalFS!J43 -> 5.5133662 | ... L30: =(HistoricalFS!L37-HistoricalFS!L40)/HistoricalFS!L43 -> 5.551273 | N30: =AVERAGE(C30:L30) -> 5.8945529 | O30: =MEDIAN(C30:L30) -> 5.5323196
B32: Debtor Turnover Ratio | C32: =HistoricalFS!C12/HistoricalFS!C80 -> 37.171823 | D32: =HistoricalFS!D12/HistoricalFS!D80 -> 22.262774 | E32: =HistoricalFS!E12/HistoricalFS!E80 -> 18.888531 | F32: =HistoricalFS!F12/HistoricalFS!F80 -> 30.356074 | G32: =HistoricalFS!G12/HistoricalFS!G80 -> 24.524403 | H32: =HistoricalFS!H12/HistoricalFS!H80 -> 29.385491 | I32: =HistoricalFS!I12/HistoricalFS!I80 -> 30.806946 | J32: =HistoricalFS!J12/HistoricalFS!J80 -> 28.425477 | ... L32: =HistoricalFS!L12/HistoricalFS!L80 -> 18.050298 | N32: =AVERAGE(C32:L32) -> 26.273025 | O32: =MEDIAN(C32:L32) -> 26.47494
B33: Creditor Turnover Ratio | C33: =HistoricalFS!C22/HistoricalFS!C71 -> 1.0950633 | D33: =HistoricalFS!D22/HistoricalFS!D71 -> 1.1149055 | E33: =HistoricalFS!E22/HistoricalFS!E71 -> 1.4559979 | F33: =HistoricalFS!F22/HistoricalFS!F71 -> 1.2569693 | G33: =HistoricalFS!G22/HistoricalFS!G71 -> 0.98988652 | H33: =HistoricalFS!H22/HistoricalFS!H71 -> 1.3582788 | I33: =HistoricalFS!I22/HistoricalFS!I71 -> 1.5703075 | J33: =HistoricalFS!J22/HistoricalFS!J71 -> 1.0744375 | ... L33: =HistoricalFS!L22/HistoricalFS!L71 -> 0.88734185 | N33: =AVERAGE(C33:L33) -> 1.1780453 | O33: =MEDIAN(C33:L33) -> 1.1049844
B34: Inventory Turnover | C34: =HistoricalFS!C22/HistoricalFS!C81 -> 5.0472105 | D34: =HistoricalFS!D22/HistoricalFS!D81 -> 5.0932656 | E34: =HistoricalFS!E22/HistoricalFS!E81 -> 6.5256879 | F34: =HistoricalFS!F22/HistoricalFS!F81 -> 6.1011732 | G34: =HistoricalFS!G22/HistoricalFS!G81 -> 4.132175 | H34: =HistoricalFS!H22/HistoricalFS!H81 -> 5.0407597 | I34: =HistoricalFS!I22/HistoricalFS!I81 -> 4.9164191 | J34: =HistoricalFS!J22/HistoricalFS!J81 -> 4.2961183 | ... L34: =HistoricalFS!L22/HistoricalFS!L81 -> 4.6272575 | N34: =AVERAGE(C34:L34) -> 5.0679034 | O34: =MEDIAN(C34:L34) -> 4.9785894
B35: Fixed Asset Turnover | C35: =HistoricalFS!C12/HistoricalFS!C74 -> 1.5310539 | D35: =HistoricalFS!D12/HistoricalFS!D74 -> 0.96765911 | E35: =HistoricalFS!E12/HistoricalFS!E74 -> 1.4266418 | F35: =HistoricalFS!F12/HistoricalFS!F74 -> 1.1201916 | G35: =HistoricalFS!G12/HistoricalFS!G74 -> 0.86152445 | H35: =HistoricalFS!H12/HistoricalFS!H74 -> 1.1065231 | I35: =HistoricalFS!I12/HistoricalFS!I74 -> 1.2091473 | J35: =HistoricalFS!J12/HistoricalFS!J74 -> 1.1526388 | ... L35: =HistoricalFS!L12/HistoricalFS!L74 -> 0.93864215 | N35: =AVERAGE(C35:L35) -> 1.1277427 | O35: =MEDIAN(C35:L35) -> 1.1133573
B36: Capital Turnover Ratio | C36: =HistoricalFS!C12/SUM(HistoricalFS!C68:C69) -> 1.1526114 | D36: =HistoricalFS!D12/SUM(HistoricalFS!D68:D69) -> 1.3315673 | E36: =HistoricalFS!E12/SUM(HistoricalFS!E68:E69) -> 1.4681462 | F36: =HistoricalFS!F12/SUM(HistoricalFS!F68:F69) -> 1.3284153 | G36: =HistoricalFS!G12/SUM(HistoricalFS!G68:G69) -> 0.66598921 | H36: =HistoricalFS!H12/SUM(HistoricalFS!H68:H69) -> 0.89119483 | I36: =HistoricalFS!I12/SUM(HistoricalFS!I68:I69) -> 1.2242356 | J36: =HistoricalFS!J12/SUM(HistoricalFS!J68:J69) -> 1.1330341 | ... L36: =HistoricalFS!L12/SUM(HistoricalFS!L68:L69) -> 1.1678595 | N36: =AVERAGE(C36:L36) -> 1.1504918 | O36: =MEDIAN(C36:L36) -> 1.1602354
B38: Debtor Days | C38: =365/C32 -> 9.8192654 | D38: =365/D32 -> 16.395082 | E38: =365/E32 -> 19.323896 | F38: =365/F32 -> 12.023953 | G38: =365/G32 -> 14.883135 | H38: =365/H32 -> 12.421096 | I38: =365/I32 -> 11.847977 | J38: =365/J32 -> 12.840593 | ... L38: =365/L32 -> 20.221272 | N38: =AVERAGE(C38:L38) -> 14.574412 | O38: =MEDIAN(C38:L38) -> 13.861864
B39: Payable Days | C39: =365/C33 -> 333.31405 | D39: =365/D33 -> 327.382 | E39: =365/E33 -> 250.68717 | F39: =365/F33 -> 290.381 | G39: =365/G33 -> 368.72914 | H39: =365/H33 -> 268.72244 | I39: =365/I33 -> 232.43855 | J39: =365/J33 -> 339.71264 | ... L39: =365/L33 -> 411.3409 | N39: =AVERAGE(C39:L39) -> 319.61995 | O39: =MEDIAN(C39:L39) -> 330.34803
B40: Inventory Days | C40: =365/C34 -> 72.317174 | D40: =365/D34 -> 71.663257 | E40: =365/E34 -> 55.932801 | F40: =365/F34 -> 59.82456 | G40: =365/G34 -> 88.331205 | H40: =365/H34 -> 72.40972 | I40: =365/I34 -> 74.241027 | J40: =365/J34 -> 84.960416 | ... L40: =365/L34 -> 78.880416 | N40: =AVERAGE(C40:L40) -> 73.306607 | O40: =MEDIAN(C40:L40) -> 73.325374
B41: Cash Conversion Cycle (in days) | C41: =SUM(C38,C40)-C39 -> -251.17761 | D41: =SUM(D38,D40)-D39 -> -239.32366 | E41: =SUM(E38,E40)-E39 -> -175.43047 | F41: =SUM(F38,F40)-F39 -> -218.53249 | G41: =SUM(G38,G40)-G39 -> -265.5148 | H41: =SUM(H38,H40)-H39 -> -183.89163 | I41: =SUM(I38,I40)-I39 -> -146.34955 | J41: =SUM(J38,J40)-J39 -> -241.91163 | ... L41: =SUM(L38,L40)-L39 -> -312.23922 | N41: =AVERAGE(C41:L41) -> -231.73893 | O41: =MEDIAN(C41:L41) -> -240.61765
B43: CFO/Sales | C43: =HistoricalFS!C90/HistoricalFS!C12 -> 0.16301809 | D43: =HistoricalFS!D90/HistoricalFS!D12 -> 0.18284236 | E43: =HistoricalFS!E90/HistoricalFS!E12 -> 0.07450861 | F43: =HistoricalFS!F90/HistoricalFS!F12 -> 0.15900845 | G43: =HistoricalFS!G90/HistoricalFS!G12 -> 0.057811699 | H43: =HistoricalFS!H90/HistoricalFS!H12 -> 0.15928933 | I43: =HistoricalFS!I90/HistoricalFS!I12 -> 0.13125573 | J43: =HistoricalFS!J90/HistoricalFS!J12 -> 0.17661931 | ... L43: =HistoricalFS!L90/HistoricalFS!L12 -> 0.1819631 | N43: =AVERAGE(C43:L43) -> 0.14719204 | O43: =MEDIAN(C43:L43) -> 0.16115371
B44: CFO/Total Assets | C44: =HistoricalFS!C90/HistoricalFS!C85 -> 0.070104499 | D44: =HistoricalFS!D90/HistoricalFS!D85 -> 0.088082557 | E44: =HistoricalFS!E90/HistoricalFS!E85 -> 0.042446598 | F44: =HistoricalFS!F90/HistoricalFS!F85 -> 0.081578484 | G44: =HistoricalFS!G90/HistoricalFS!G85 -> 0.020421722 | H44: =HistoricalFS!H90/HistoricalFS!H85 -> 0.073837165 | I44: =HistoricalFS!I90/HistoricalFS!I85 -> 0.071631664 | J44: =HistoricalFS!J90/HistoricalFS!J85 -> 0.090475018 | ... L44: =HistoricalFS!L90/HistoricalFS!L85 -> 0.088224543 | N44: =AVERAGE(C44:L44) -> 0.07184583 | O44: =MEDIAN(C44:L44) -> 0.077707824
B45: CFO/Total Debt | C45: =HistoricalFS!C90/HistoricalFS!C70 -> 0.22784228 | D45: =HistoricalFS!D90/HistoricalFS!D70 -> 0.29794074 | E45: =HistoricalFS!E90/HistoricalFS!E70 -> 0.1376148 | F45: =HistoricalFS!F90/HistoricalFS!F70 -> 0.26715906 | G45: =HistoricalFS!G90/HistoricalFS!G70 -> 0.096636818 | H45: =HistoricalFS!H90/HistoricalFS!H70 -> 0.34670602 | I45: =HistoricalFS!I90/HistoricalFS!I70 -> 0.2546849 | J45: =HistoricalFS!J90/HistoricalFS!J70 -> 0.45274992 | ... L45: =HistoricalFS!L90/HistoricalFS!L70 -> 0.47675215 | N45: =AVERAGE(C45:L45) -> 0.30355026 | O45: =MEDIAN(C45:L45) -> 0.2825499

Sheet Common Size Statement
B8: INR Crores | C8: =HistoricalFS!C9 -> 42825 | D8: =HistoricalFS!D9 -> 43190 | E8: =HistoricalFS!E9 -> 43555 | F8: =HistoricalFS!F9 -> 43921 | G8: =HistoricalFS!G9 -> 44286 | H8: =HistoricalFS!H9 -> 44651 | I8: =HistoricalFS!I9 -> 45016 | J8: =HistoricalFS!J9 -> 45382 | ... L8: =HistoricalFS!L9 -> 46112
A9: # | B9: Common Size Statement
B11: Sales | C11: =C37/C37 -> 1 | D11: =D37/D37 -> 1 | E11: =E37/E37 -> 1 | F11: =F37/F37 -> 1 | G11: =G37/G37 -> 1 | H11: =H37/H37 -> 1 | I11: =I37/I37 -> 1 | J11: =J37/J37 -> 1 | ... L11: =L37/L37 -> 1
B13: COGS | C13: =C40/C$37 -> 0.8128401 | D13: =D40/D$37 -> 0.79283717 | E13: =E40/E$37 -> 0.77574045 | F13: =F40/F$37 -> 0.75567432 | G13: =G40/G$37 -> 0.72373565 | H13: =H40/H$37 -> 0.78207013 | I13: =I40/I$37 -> 0.78541892 | J13: =J40/J$37 -> 0.7300201 | ... L13: =L40/L$37 -> 0.73166664
B15: Gross Profit | C15: =C42/C$37 -> 0.20432697 | D15: =D42/D$37 -> 0.22919327 | E15: =E42/E$37 -> 0.2324941 | F15: =F42/F$37 -> 0.25278584 | G15: =G42/G$37 -> 0.29570219 | H15: =H42/H$37 -> 0.24881779 | I15: =I42/I$37 -> 0.24911227 | J15: =J42/J$37 -> 0.27541124 | ... L15: =L42/L$37 -> 0.27805793
B17: Selling and admin | C17: =C44/C$37 -> 0.060930272 | D17: =D44/D$37 -> 0.074486404 | E17: =E44/E$37 -> 0.088364826 | F17: =F44/F$37 -> 0.1049509 | G17: =G44/G$37 -> 0.12042281 | H17: =H44/H$37 -> 0.091428629 | I17: =I44/I$37 -> 0.076870501 | J17: =J44/J$37 -> 0.085971608 | ... L17: =L44/L$37 -> 0.099190172
B19: Other Income | C19: =C46/C$37 -> 0.030340117 | D19: =D46/D$37 -> 0.02525184 | E19: =E46/E$37 -> 0.01479052 | F19: =F46/F$37 -> 0.014362832 | G19: =G46/G$37 -> 0.048105647 | H19: =H46/H$37 -> 0.028214714 | I19: =I46/I$37 -> 0.013715261 | J19: =J46/J$37 -> 0.017565384 | ... L19: =L46/L$37 -> 0.02732198
B21: Other Expenses | C21: =C48/C$37 -> -0.0089520125 | D21: =D48/D$37 -> -0.0098561241 | E21: =E48/E$37 -> -0.0041102374 | F21: =F48/F$37 -> -0.0017697958 | G21: =G48/G$37 -> 0.0020244174 | H21: =H48/H$37 -> 0.0010839632 | I21: =I48/I$37 -> 0.0098517109 | J21: =J48/J$37 -> 0.0086937081 | ... L21: =L48/L$37 -> 0.0092632935
B23: EBITDA | C23: =C50/C$37 -> 0.18268883 | D23: =D50/D$37 -> 0.18981483 | E23: =E50/E$37 -> 0.16303003 | F23: =F50/F$37 -> 0.16396756 | G23: =G50/G$37 -> 0.22136061 | H23: =H50/H$37 -> 0.18451991 | I23: =I50/I$37 -> 0.17610532 | J23: =J50/J$37 -> 0.19831131 | ... L23: =L50/L$37 -> 0.19692644
B25: Depreciation | C25: =C52/C$37 -> 0.038315008 | D25: =D52/D$37 -> 0.042745693 | E25: =E52/E$37 -> 0.03683378 | F25: =F52/F$37 -> 0.037210963 | G25: =G52/G$37 -> 0.056983918 | H25: =H52/H$37 -> 0.04287197 | I25: =I52/I$37 -> 0.045987202 | J25: =J52/J$37 -> 0.056540247 | ... L25: =L52/L$37 -> 0.054640171
B27: Interest | C27: =C54/C$37 -> 0.0126631 | D27: =D54/D$37 -> 0.020602677 | E27: =E54/E$37 -> 0.029023273 | F27: =F54/F$37 -> 0.036915997 | G27: =G54/G$37 -> 0.045440021 | H27: =H54/H$37 -> 0.02099405 | I27: =I54/I$37 -> 0.022331229 | J27: =J54/J$37 -> 0.025714066 | ... L27: =L54/L$37 -> 0.025631287
B29: Earning Before Tax | C29: =C56/C$37 -> 0.13171072 | D29: =D56/D$37 -> 0.12646646 | E29: =E56/E$37 -> 0.09717298 | F29: =F56/F$37 -> 0.089840601 | G29: =G56/G$37 -> 0.11893667 | H29: =H56/H$37 -> 0.12065389 | I29: =I56/I$37 -> 0.10778689 | J29: =J56/J$37 -> 0.116057 | ... L29: =L56/L$37 -> 0.11665498
B31: Tax | C31: =C58/C$37 -> 0.033560999 | D31: =D58/D$37 -> 0.034148451 | E31: =E58/E$37 -> 0.027079004 | F31: =F58/F$37 -> 0.023003994 | G31: =G58/G$37 -> 0.0036928461 | H31: =H58/H$37 -> 0.022989234 | I31: =I58/I$37 -> 0.023249764 | J31: =J58/J$37 -> 0.028593802 | ... L31: =L58/L$37 -> 0.026096346
B33: Net Profit | C33: =C60/C$37 -> 0.09814972 | D33: =D60/D$37 -> 0.092318006 | E33: =E60/E$37 -> 0.070093976 | F33: =F60/F$37 -> 0.066836607 | G33: =G60/G$37 -> 0.11524382 | H33: =H60/H$37 -> 0.097664657 | I33: =I60/I$37 -> 0.084537127 | J33: =J60/J$37 -> 0.087463197 | ... L33: =L60/L$37 -> 0.090558639
A35: # | B35: Historical Financial Statement
B36: Change Analysis | C36: 0
B37: Sales | C37: =HistoricalFS!C12*(1+$C$36) -> 303954 | D37: =HistoricalFS!D12*(1+$C$36) -> 390823 | E37: =HistoricalFS!E12*(1+$C$36) -> 568337 | F37: =HistoricalFS!F12*(1+$C$36) -> 596679 | G37: =HistoricalFS!G12*(1+$C$36) -> 466307 | H37: =HistoricalFS!H12*(1+$C$36) -> 694673 | I37: =HistoricalFS!I12*(1+$C$36) -> 876396 | J37: =HistoricalFS!J12*(1+$C$36) -> 899041 | ... L37: =HistoricalFS!L12*(1+$C$36) -> 1055780
B38: Changes In Inventory | C38: =HistoricalFS!C15*(1+$C$36) -> 5218 | D38: =HistoricalFS!D15*(1+$C$36) -> 8610 | E38: =HistoricalFS!E15*(1+$C$36) -> 4680 | F38: =HistoricalFS!F15*(1+$C$36) -> 5048 | G38: =HistoricalFS!G15*(1+$C$36) -> 9064 | H38: =HistoricalFS!H15*(1+$C$36) -> 21457 | I38: =HistoricalFS!I15*(1+$C$36) -> 30263 | J38: =HistoricalFS!J15*(1+$C$36) -> 4883 | ... L38: =HistoricalFS!L15*(1+$C$36) -> 10267
B40: COGS | C40: =HistoricalFS!C22*(1+$C$36) -> 247066 | D40: =HistoricalFS!D22*(1+$C$36) -> 309859 | E40: =HistoricalFS!E22*(1+$C$36) -> 440882 | F40: =HistoricalFS!F22*(1+$C$36) -> 450895 | G40: =HistoricalFS!G22*(1+$C$36) -> 337483 | H40: =HistoricalFS!H22*(1+$C$36) -> 543283 | I40: =HistoricalFS!I22*(1+$C$36) -> 688338 | J40: =HistoricalFS!J22*(1+$C$36) -> 656318 | ... L40: =HistoricalFS!L22*(1+$C$36) -> 772479
B42: Gross Profit | C42: =HistoricalFS!C25*(1+$C$36) -> 62106 | D42: =HistoricalFS!D25*(1+$C$36) -> 89574 | E42: =HistoricalFS!E25*(1+$C$36) -> 132135 | F42: =HistoricalFS!F25*(1+$C$36) -> 150832 | G42: =HistoricalFS!G25*(1+$C$36) -> 137888 | H42: =HistoricalFS!H25*(1+$C$36) -> 172847 | I42: =HistoricalFS!I25*(1+$C$36) -> 218321 | J42: =HistoricalFS!J25*(1+$C$36) -> 247606 | ... L42: =HistoricalFS!L25*(1+$C$36) -> 293568
B44: Selling and admin | C44: =HistoricalFS!C28*(1+$C$36) -> 18520 | D44: =HistoricalFS!D28*(1+$C$36) -> 29111 | E44: =HistoricalFS!E28*(1+$C$36) -> 50221 | F44: =HistoricalFS!F28*(1+$C$36) -> 62622 | G44: =HistoricalFS!G28*(1+$C$36) -> 56154 | H44: =HistoricalFS!H28*(1+$C$36) -> 63513 | I44: =HistoricalFS!I28*(1+$C$36) -> 67369 | J44: =HistoricalFS!J28*(1+$C$36) -> 77292 | ... L44: =HistoricalFS!L28*(1+$C$36) -> 104723
B46: Other Income | C46: =HistoricalFS!C31*(1+$C$36) -> 9222 | D46: =HistoricalFS!D31*(1+$C$36) -> 9869 | E46: =HistoricalFS!E31*(1+$C$36) -> 8406 | F46: =HistoricalFS!F31*(1+$C$36) -> 8570 | G46: =HistoricalFS!G31*(1+$C$36) -> 22432 | H46: =HistoricalFS!H31*(1+$C$36) -> 19600 | I46: =HistoricalFS!I31*(1+$C$36) -> 12020 | J46: =HistoricalFS!J31*(1+$C$36) -> 15792 | ... L46: =HistoricalFS!L31*(1+$C$36) -> 28846
B48: Other Expenses | C48: =HistoricalFS!C34*(1+$C$36) -> -2721 | D48: =HistoricalFS!D34*(1+$C$36) -> -3852 | E48: =HistoricalFS!E34*(1+$C$36) -> -2336 | F48: =HistoricalFS!F34*(1+$C$36) -> -1056 | G48: =HistoricalFS!G34*(1+$C$36) -> 944 | H48: =HistoricalFS!H34*(1+$C$36) -> 753 | I48: =HistoricalFS!I34*(1+$C$36) -> 8634 | J48: =HistoricalFS!J34*(1+$C$36) -> 7816 | ... L48: =HistoricalFS!L34*(1+$C$36) -> 9780
B50: EBITDA | C50: =HistoricalFS!C37*(1+$C$36) -> 55529 | D50: =HistoricalFS!D37*(1+$C$36) -> 74184 | E50: =HistoricalFS!E37*(1+$C$36) -> 92656 | F50: =HistoricalFS!F37*(1+$C$36) -> 97836 | G50: =HistoricalFS!G37*(1+$C$36) -> 103222 | H50: =HistoricalFS!H37*(1+$C$36) -> 128181 | I50: =HistoricalFS!I37*(1+$C$36) -> 154338 | J50: =HistoricalFS!J37*(1+$C$36) -> 178290 | ... L50: =HistoricalFS!L37*(1+$C$36) -> 207911
B52: Depreciation | C52: =HistoricalFS!C40*(1+$C$36) -> 11646 | D52: =HistoricalFS!D40*(1+$C$36) -> 16706 | E52: =HistoricalFS!E40*(1+$C$36) -> 20934 | F52: =HistoricalFS!F40*(1+$C$36) -> 22203 | G52: =HistoricalFS!G40*(1+$C$36) -> 26572 | H52: =HistoricalFS!H40*(1+$C$36) -> 29782 | I52: =HistoricalFS!I40*(1+$C$36) -> 40303 | J52: =HistoricalFS!J40*(1+$C$36) -> 50832 | ... L52: =HistoricalFS!L40*(1+$C$36) -> 57688
B54: Interest | C54: =HistoricalFS!C43*(1+$C$36) -> 3849 | D54: =HistoricalFS!D43*(1+$C$36) -> 8052 | E54: =HistoricalFS!E43*(1+$C$36) -> 16495 | F54: =HistoricalFS!F43*(1+$C$36) -> 22027 | G54: =HistoricalFS!G43*(1+$C$36) -> 21189 | H54: =HistoricalFS!H43*(1+$C$36) -> 14584 | I54: =HistoricalFS!I43*(1+$C$36) -> 19571 | J54: =HistoricalFS!J43*(1+$C$36) -> 23118 | ... L54: =HistoricalFS!L43*(1+$C$36) -> 27061
B56: Earning Before Tax | C56: =HistoricalFS!C46*(1+$C$36) -> 40034 | D56: =HistoricalFS!D46*(1+$C$36) -> 49426 | E56: =HistoricalFS!E46*(1+$C$36) -> 55227 | F56: =HistoricalFS!F46*(1+$C$36) -> 53606 | G56: =HistoricalFS!G46*(1+$C$36) -> 55461 | H56: =HistoricalFS!H46*(1+$C$36) -> 83815 | I56: =HistoricalFS!I46*(1+$C$36) -> 94464 | J56: =HistoricalFS!J46*(1+$C$36) -> 104340 | ... L56: =HistoricalFS!L46*(1+$C$36) -> 123162
B58: Tax | C58: =HistoricalFS!C49*(1+$C$36) -> 10201 | D58: =HistoricalFS!D49*(1+$C$36) -> 13346 | E58: =HistoricalFS!E49*(1+$C$36) -> 15390 | F58: =HistoricalFS!F49*(1+$C$36) -> 13726 | G58: =HistoricalFS!G49*(1+$C$36) -> 1722 | H58: =HistoricalFS!H49*(1+$C$36) -> 15970 | I58: =HistoricalFS!I49*(1+$C$36) -> 20376 | J58: =HistoricalFS!J49*(1+$C$36) -> 25707 | ... L58: =HistoricalFS!L49*(1+$C$36) -> 27552
B60: Net Profit | C60: =HistoricalFS!C52*(1+$C$36) -> 29833 | D60: =HistoricalFS!D52*(1+$C$36) -> 36080 | E60: =HistoricalFS!E52*(1+$C$36) -> 39837 | F60: =HistoricalFS!F52*(1+$C$36) -> 39880 | G60: =HistoricalFS!G52*(1+$C$36) -> 53739 | H60: =HistoricalFS!H52*(1+$C$36) -> 67845 | I60: =HistoricalFS!I52*(1+$C$36) -> 74088 | J60: =HistoricalFS!J52*(1+$C$36) -> 78633 | ... L60: =HistoricalFS!L52*(1+$C$36) -> 95610

Sheet Forcasting
B12: Forcasting of Revenue | H12: SUMMARY OUTPUT
B14: Year Weight | C14: Year | D14: Sales | E14: Sales Growth | H14: Regression Statistics
B15: 1 | C15: ='Ratio Analysis'!C9 -> 42825 | D15: 303954 | H15: Multiple R | I15: 0.96035656
B16: =B15+1 -> 2 | C16: =C15+365 -> 43190 | D16: 390823 | E16: =D16/D15-1 -> 0.28579654 | H16: R Square | I16: 0.92228471
B17: =B16+1 -> 3 | C17: =C16+365 -> 43555 | D17: 568337 | E17: =D17/D16-1 -> 0.45420561 | H17: Adjusted R Square | I17: 0.9125703
B18: =B17+1 -> 4 | C18: =C17+365 -> 43920 | D18: 596679 | E18: =D18/D17-1 -> 0.0498683 | H18: Standard Error | I18: 76221.481
B19: =B18+1 -> 5 | C19: =C18+365 -> 44285 | D19: 466307 | E19: =D19/D18-1 -> -0.21849604 | H19: Observations | I19: 10
B20: =B19+1 -> 6 | C20: =C19+365 -> 44650 | D20: 694673 | E20: =D20/D19-1 -> 0.48973316
B21: =B20+1 -> 7 | C21: =C20+365 -> 45015 | D21: 876396 | E21: =D21/D20-1 -> 0.26159502 | H21: ANOVA
B22: =B21+1 -> 8 | C22: =C21+365 -> 45380 | D22: 899041 | E22: =D22/D21-1 -> 0.025838776 | I22: df | J22: SS | K22: MS | L22: F | M22: Significance F
B23: =B22+1 -> 9 | C23: =C22+365 -> 45745 | D23: 962820 | E23: =D23/D22-1 -> 0.070941147 | H23: Regression | I23: 1 | J23: 5.515734e+11 | K23: 5.515734e+11 | L23: 94.939852 | M23: 1.0300346e-05
B24: =B23+1 -> 10 | C24: =C23+365 -> 46110 | D24: 1055780 | E24: =D24/D23-1 -> 0.096549719 | H24: Residual | I24: 8 | J24: 4.6477714e+10 | K24: 5.8097142e+09
B25: =B24+1 -> 11 | C25: =C24+365 -> 46475 | D25: =$I$28+B25*$I$29 -> 1131196 | E25: =D25/D24-1 -> 0.071431548 | H25: Total | I25: 9 | J25: 598051116920
B26: =B25+1 -> 12 | C26: =C25+365 -> 46840 | D26: =$I$28+B26*$I$29 -> 1212962.4 | E26: =D26/D25-1 -> 0.072283109
B27: =B26+1 -> 13 | C27: =C26+365 -> 47205 | D27: =$I$28+B27*$I$29 -> 1294728.7 | E27: =D27/D26-1 -> 0.067410471 | I27: Coefficients | J27: Standard Error | K27: t Stat | L27: P-value | M27: Lower 95% | N27: Upper 95% | O27: Lower 95.0% | P27: Upper 95.0%
B28: =B27+1 -> 14 | C28: =C27+365 -> 47570 | D28: =$I$28+B28*$I$29 -> 1376495.1 | E28: =D28/D27-1 -> 0.063153278 | H28: Intercept | I28: 231766 | J28: 52069.184 | K28: 4.4511164 | L28: 0.0021361276 | M28: 111694.25 | N28: 351837.75 | O28: 111694.25 | P28: 351837.75
H29: Year Weight | I29: 81766.364 | J29: 8391.7089 | K29: 9.7437083 | L29: 1.0300346e-05 | M29: 62415.048 | N29: 101117.68 | O29: 62415.048 | P29: 101117.68

Sheet intrinsic Growth
B8: Calculation Of ROIC | C8: =RawFs!E2 -> 42795 | D8: =RawFs!F2 -> 43160 | E8: =RawFs!G2 -> 43525 | F8: =RawFs!H2 -> 43891 | G8: =RawFs!I2 -> 44256 | H8: =RawFs!J2 -> 44621 | I8: =RawFs!K2 -> 44986 | J8: =RawFs!L2 -> 45352 | ... L8: =RawFs!N2 -> 46082
A10: # | B10: Current Asset
B11: Inventories | C11: =RawFs!E31 -> 48951 | D11: =RawFs!F31 -> 60837 | E11: =RawFs!G31 -> 67561 | F11: =RawFs!H31 -> 73903 | G11: =RawFs!I31 -> 81672 | H11: =RawFs!J31 -> 107778 | I11: =RawFs!K31 -> 140008 | J11: =RawFs!L31 -> 152770 | ... L11: =RawFs!N31 -> 166941
B12: Trade Receivables | C12: =RawFs!E32 -> 8177 | D12: =RawFs!F32 -> 17555 | E12: =RawFs!G32 -> 30089 | F12: =RawFs!H32 -> 19656 | G12: =RawFs!I32 -> 19014 | H12: =RawFs!J32 -> 23640 | I12: =RawFs!K32 -> 28448 | J12: =RawFs!L32 -> 31628 | ... L12: =RawFs!N32 -> 58491
B13: Loan n Advances | C13: =RawFs!E34 -> 996 | D13: =RawFs!F34 -> 2327 | E13: =RawFs!G34 -> 545 | F13: =RawFs!H34 -> 669 | G13: =RawFs!I34 -> 65 | H13: =RawFs!J34 -> 130 | I13: =RawFs!K34 -> 176 | J13: =RawFs!L34 -> 2517 | ... L13: =RawFs!N34 -> 4870
B14: Other Assets Items | C14: =RawFs!E35 -> 39393 | D14: =RawFs!F35 -> 52530 | E14: =RawFs!G35 -> 74882 | F14: =RawFs!H35 -> 119336 | G14: =RawFs!I35 -> 169878 | H14: =RawFs!J35 -> 136328 | I14: =RawFs!K35 -> 114469 | J14: =RawFs!L35 -> 126396 | ... L14: =RawFs!N35 -> 190454
B15: Total Assets | C15: =SUM(C11:C14) -> 97517 | D15: =SUM(D11:D14) -> 133249 | E15: =SUM(E11:E14) -> 173077 | F15: =SUM(F11:F14) -> 213564 | G15: =SUM(G11:G14) -> 270629 | H15: =SUM(H11:H14) -> 267876 | I15: =SUM(I11:I14) -> 283101 | J15: =SUM(J11:J14) -> 313311 | ... L15: =SUM(L11:L14) -> 420756
B17: Current Liabilities
B18: Trade Payable | C18: =RawFs!E12 -> 76595 | D18: =RawFs!F12 -> 106861 | E18: =RawFs!G12 -> 108309 | F18: =RawFs!H12 -> 96799 | G18: =RawFs!I12 -> 108897 | H18: =RawFs!J12 -> 159330 | I18: =RawFs!K12 -> 147172 | J18: =RawFs!L12 -> 178377 | ... L18: =RawFs!N12 -> 158842
B19: Other Liablities | C19: =RawFs!E13 -> 146106 | D19: =RawFs!F13 -> 167524 | E19: =RawFs!G13 -> 186215 | F19: =RawFs!H13 -> 249736 | G19: =RawFs!I13 -> 132774 | H19: =RawFs!J13 -> 131150 | I19: =RawFs!K13 -> 178165 | J19: =RawFs!L13 -> 300164 | ... L19: =RawFs!N13 -> 529876
A21: # | B21: Total Liabilities | C21: =SUM(C18:C20) -> 222701 | D21: =SUM(D18:D20) -> 274385 | E21: =SUM(E18:E20) -> 294524 | F21: =SUM(F18:F20) -> 346535 | G21: =SUM(G18:G20) -> 241671 | H21: =SUM(H18:H20) -> 290480 | I21: =SUM(I18:I20) -> 325337 | J21: =SUM(J18:J20) -> 478541 | ... L21: =SUM(L18:L20) -> 688718
A23: # | B23: Net Working Capital | C23: =C15-C21 -> -125184 | D23: =D15-D21 -> -141136 | E23: =E15-E21 -> -121447 | F23: =F15-F21 -> -132971 | G23: =G15-G21 -> 28958 | H23: =H15-H21 -> -22604 | I23: =I15-I21 -> -42236 | J23: =J15-J21 -> -165230 | ... L23: =L15-L21 -> -267962
A25: # | B25: Non Current Assets
B26: Land | C26: =RawFs!E17 -> 65973 | D26: =RawFs!F17 -> 66765 | E26: =RawFs!G17 -> 49371 | F26: =RawFs!H17 -> 68743 | G26: =RawFs!I17 -> 68768 | H26: =RawFs!J17 -> 69855 | I26: =RawFs!K17 -> 79697 | J26: =RawFs!L17 -> 87287 | ... L26: =RawFs!N17 -> 103974
B27: Building | C27: =RawFs!E18 -> 18813 | D27: =RawFs!F18 -> 22194 | E27: =RawFs!G18 -> 27672 | F27: =RawFs!H18 -> 34380 | G27: =RawFs!I18 -> 36781 | H27: =RawFs!J18 -> 47561 | I27: =RawFs!K18 -> 69747 | J27: =RawFs!L18 -> 82062 | ... L27: =RawFs!N18 -> 110548
B28: Plant Machinery | C28: =RawFs!E19 -> 179326 | D28: =RawFs!F19 -> 325183 | E28: =RawFs!G19 -> 318853 | F28: =RawFs!H19 -> 449770 | G28: =RawFs!I19 -> 471201 | H28: =RawFs!J19 -> 518865 | I28: =RawFs!K19 -> 557687 | J28: =RawFs!L19 -> 579067 | ... L28: =RawFs!N19 -> 727877
B29: Ships Vessels | C29: =RawFs!E20 -> 3484 | D29: =RawFs!F20 -> 5038 | E29: =RawFs!G20 -> 417 | F29: =RawFs!H20 -> 502 | G29: =RawFs!I20 -> 515 | H29: =RawFs!J20 -> 508 | I29: =RawFs!K20 -> 518 | J29: =RawFs!L20 -> 522 | ... L29: =RawFs!N20 -> 551
B30: Equipments | C30: =RawFs!E21 -> 0 | D30: =RawFs!F21 -> 0 | E30: =RawFs!G21 -> 0 | F30: =RawFs!H21 -> 0 | G30: =RawFs!I21 -> 0 | H30: =RawFs!J21 -> 32638 | I30: =RawFs!K21 -> 45067 | J30: =RawFs!L21 -> 59936 | ... L30: =RawFs!N21 -> 0
B31: Furniture n fittings | C31: =RawFs!E22 -> 7848 | D31: =RawFs!F22 -> 10146 | E31: =RawFs!G22 -> 21817 | F31: =RawFs!H22 -> 31211 | G31: =RawFs!I22 -> 38039 | H31: =RawFs!J22 -> 24970 | I31: =RawFs!K22 -> 38161 | J31: =RawFs!L22 -> 43458 | ... L31: =RawFs!N22 -> 121211
B32: Vehicles | C32: =RawFs!E23 -> 1155 | D32: =RawFs!F23 -> 1199 | E32: =RawFs!G23 -> 1240 | F32: =RawFs!H23 -> 1411 | G32: =RawFs!I23 -> 2336 | H32: =RawFs!J23 -> 2530 | I32: =RawFs!K23 -> 3667 | J32: =RawFs!L23 -> 3745 | ... L32: =RawFs!N23 -> 5044
B33: Intangible Assets | C33: =RawFs!E24 -> 75351 | D33: =RawFs!F24 -> 76599 | E33: =RawFs!G24 -> 86765 | F33: =RawFs!H24 -> 81462 | G33: =RawFs!I24 -> 77353 | H33: =RawFs!J24 -> 65970 | I33: =RawFs!K24 -> 85032 | J33: =RawFs!L24 -> 112873 | ... L33: =RawFs!N24 -> 167504
B34: Other fixed assets | C34: =RawFs!E25 -> 9343 | D34: =RawFs!F25 -> 74160 | E34: =RawFs!G25 -> 90387 | F34: =RawFs!H25 -> 76299 | G34: =RawFs!I25 -> 80819 | H34: =RawFs!J25 -> 120717 | I34: =RawFs!K25 -> 138426 | J34: =RawFs!L25 -> 145632 | ... L34: =RawFs!N25 -> 318878
B35: Gross Block | C35: =SUM(C26:C34) -> 361293 | D35: =SUM(D26:D34) -> 581284 | E35: =SUM(E26:E34) -> 596522 | F35: =SUM(F26:F34) -> 743778 | G35: =SUM(G26:G34) -> 775812 | H35: =SUM(H26:H34) -> 883614 | I35: =SUM(I26:I34) -> 1018002 | J35: =SUM(J26:J34) -> 1114582 | ... L35: =SUM(L26:L34) -> 1555587
B36: Accumulated Depreciation | C36: =-RawFs!E27 -> -162767 | D36: =-RawFs!F27 -> -177399 | E36: =-RawFs!G27 -> -198148 | F36: =-RawFs!H27 -> -211120 | G36: =-RawFs!I27 -> -234554 | H36: =-RawFs!J27 -> -255816 | I36: =-RawFs!K27 -> -293197 | J36: =-RawFs!L27 -> -334597 | ... L36: =-RawFs!N27 -> -430792
A37: # | B37: Net Non Current Assets | C37: =SUM(C35:C36) -> 198526 | D37: =SUM(D35:D36) -> 403885 | E37: =SUM(E35:E36) -> 398374 | F37: =SUM(F35:F36) -> 532658 | G37: =SUM(G35:G36) -> 541258 | H37: =SUM(H35:H36) -> 627798 | I37: =SUM(I35:I36) -> 724805 | J37: =SUM(J35:J36) -> 779985 | ... L37: =SUM(L35:L36) -> 1124795
A40: # | B40: Invested Capital | C40: =SUM(C37,C23) -> 73342 | D40: =SUM(D37,D23) -> 262749 | E40: =SUM(E37,E23) -> 276927 | F40: =SUM(F37,F23) -> 399687 | G40: =SUM(G37,G23) -> 570216 | H40: =SUM(H37,H23) -> 605194 | I40: =SUM(I37,I23) -> 682569 | J40: =SUM(J37,J23) -> 614755 | ... L40: =SUM(L37,L23) -> 856833
B41: EBIT | C41: =SUM('Data Sheet '!B28:B29) -> 43883 | D41: =SUM('Data Sheet '!C28:C29) -> 57478 | E41: =SUM('Data Sheet '!D28:D29) -> 71722 | F41: =SUM('Data Sheet '!E28:E29) -> 75633 | G41: =SUM('Data Sheet '!F28:F29) -> 76650 | H41: =SUM('Data Sheet '!G28:G29) -> 98399 | I41: =SUM('Data Sheet '!H28:H29) -> 114035 | J41: =SUM('Data Sheet '!I28:I29) -> 127458 | ... L41: =SUM('Data Sheet '!K28:K29) -> 150223
B43: ROIC | C43: =C41/C40 -> 0.59833383 | D43: =D41/D40 -> 0.2187563 | E43: =E41/E40 -> 0.25899244 | F43: =F41/F40 -> 0.18923057 | G43: =G41/G40 -> 0.13442275 | H43: =H41/H40 -> 0.16259084 | I43: =I41/I40 -> 0.16706736 | J43: =J41/J40 -> 0.20733138 | ... L43: =L41/L40 -> 0.17532355
B45: Calculation Of Reinvestment Rate | C45: =C8 -> 42795 | D45: =D8 -> 43160 | E45: =E8 -> 43525 | F45: =F8 -> 43891 | G45: =G8 -> 44256 | H45: =H8 -> 44621 | I45: =I8 -> 44986 | J45: =J8 -> 45352 | ... L45: =L8 -> 46082
B47: Net Capex | C47: =-SUM(RawFs!E48:E49) -> 76627 | D47: =-SUM(RawFs!F48:F49) -> 72954 | E47: =-SUM(RawFs!G48:G49) -> 92777 | F47: =-SUM(RawFs!H48:H49) -> 75553 | G47: =-SUM(RawFs!I48:I49) -> 103518 | H47: =-SUM(RawFs!J48:J49) -> 97008 | I47: =-SUM(RawFs!K48:K49) -> 131802 | J47: =-SUM(RawFs!L48:L49) -> 137576 | ... L47: =-SUM(RawFs!N48:N49) -> 122090
B48: Change In Working Capital | D48: =D23-C23 -> -15952 | E48: =E23-D23 -> 19689 | F48: =F23-E23 -> -11524 | G48: =G23-F23 -> 161929 | H48: =H23-G23 -> -51562 | I48: =I23-H23 -> -19632 | J48: =J23-I23 -> -122994 | K48: =K23-J23 -> -61465 | L48: =L23-K23 -> -41267
B50: EBIT | C50: =C41 -> 43883 | D50: =D41 -> 57478 | E50: =E41 -> 71722 | F50: =F41 -> 75633 | G50: =G41 -> 76650 | H50: =H41 -> 98399 | I50: =I41 -> 114035 | J50: =J41 -> 127458 | ... L50: =L41 -> 150223
B51: Marginal Tax Rate | C51: 0.25 | D51: 0.25 | E51: 0.25 | F51: 0.25 | G51: 0.25 | H51: 0.25 | I51: 0.25 | J51: 0.25 | K51: 0.25 | L51: 0.25
B52: EBIT(1-Tax Rate) | C52: =C50*(1-C51) -> 32912.25 | D52: =D50*(1-D51) -> 43108.5 | E52: =E50*(1-E51) -> 53791.5 | F52: =F50*(1-F51) -> 56724.75 | G52: =G50*(1-G51) -> 57487.5 | H52: =H50*(1-H51) -> 73799.25 | I52: =I50*(1-I51) -> 85526.25 | J52: =J50*(1-J51) -> 95593.5 | ... L52: =L50*(1-L51) -> 112667.25
B54: Reinvestment | D54: =SUM(D47:D48) -> 57002 | E54: =SUM(E47:E48) -> 112466 | F54: =SUM(F47:F48) -> 64029 | G54: =SUM(G47:G48) -> 265447 | H54: =SUM(H47:H48) -> 45446 | I54: =SUM(I47:I48) -> 112170 | J54: =SUM(J47:J48) -> 14582 | K54: =SUM(K47:K48) -> 76159 | L54: =SUM(L47:L48) -> 80823
A55: # | B55: Reinvestment Rate | D55: =D54/D52 -> 1.3222914 | E55: =E54/E52 -> 2.0907764 | F55: =F54/F52 -> 1.1287665 | G55: =G54/G52 -> 4.6174734 | H55: =H54/H52 -> 0.61580572 | I55: =I54/I52 -> 1.3115272 | J55: =J54/J52 -> 0.15254175 | K55: =K54/K52 -> 0.77940326 | L55: =L54/L52 -> 0.71736019
K57: 4 Year Average | L57: =AVERAGE(I55:L55) -> 0.74020809
K58: 4 Year Median | L58: =MEDIAN(I55:L55) -> 0.74838173
B60: Calculation Of Growth Rate | C60: =C45 -> 42795 | D60: =D45 -> 43160 | E60: =E45 -> 43525 | F60: =F45 -> 43891 | G60: =G45 -> 44256 | H60: =H45 -> 44621 | I60: =I45 -> 44986 | J60: =J45 -> 45352 | ... L60: =L45 -> 46082
B62: Reinvestment Rate | D62: =D55 -> 1.3222914 | E62: =E55 -> 2.0907764 | F62: =F55 -> 1.1287665 | G62: =G55 -> 4.6174734 | H62: =H55 -> 0.61580572 | I62: =I55 -> 1.3115272 | J62: =J55 -> 0.15254175 | K62: =K55 -> 0.77940326 | L62: =L55 -> 0.71736019
B63: ROIC | D63: =D43 -> 0.2187563 | E63: =E43 -> 0.25899244 | F63: =F43 -> 0.18923057 | G63: =G43 -> 0.13442275 | H63: =H43 -> 0.16259084 | I63: =I43 -> 0.16706736 | J63: =J43 -> 0.20733138 | K63: =K43 -> 0.1686118 | L63: =L43 -> 0.17532355
A65: # | B65: Intrinsic Growth | D65: =D63*D62 -> 0.28925958 | E65: =E63*E62 -> 0.54149529 | F65: =F63*F62 -> 0.21359714 | G65: =G63*G62 -> 0.62069344 | H65: =H63*H62 -> 0.10012437 | I65: =I63*I62 -> 0.21911338 | J65: =J63*J62 -> 0.031626691 | K65: =K63*K62 -> 0.13141659 | L65: =L63*L62 -> 0.12577013
K67: 4 Year Average | L67: =AVERAGE(I65:L65) -> 0.1269817
K68: 4 Year Median | L68: =MEDIAN(I65:L65) -> 0.12859336

Sheet RawFs
B2: Particlar | C2: 42064 | D2: 42430 | E2: 42795 | F2: 43160 | G2: 43525 | H2: 43891 | I2: 44256 | J2: 44621 | K2: 44986 | L2: 45352 | M2: 45717 | N2: 46082
B3: Equity Capital | C3: 2943 | D3: 2948 | E3: 2959 | F3: 5922 | G3: 5926 | H3: 6339 | I3: 6445 | J3: 6765 | K3: 6766 | L3: 6766 | M3: 13532 | N3: 13532
B4: Reserves | C4: 215556 | D4: 228608 | E4: 260750 | F4: 287584 | G4: 381186 | H4: 442827 | I4: 693727 | J4: 772720 | K4: 709106 | L4: 786715 | M4: 829668 | N4: 890498
B5: Borrowings - | C5: 168251 | D5: 194714 | E5: 217475 | F5: 239843 | G5: 307714 | H5: 355133 | I5: 278962 | J5: 319158 | K5: 451664 | L5: 350719 | M5: 374313 | N5: 402962
B6: Long term Borrowings | C6: 128165 | D6: 154957 | E6: 172285 | F6: 164385 | G6: 226345 | H6: 216470 | I6: 182520 | J6: 224883 | K6: 296023 | L6: 222712 | M6: 236899 | N6: 270751
B7: Short term Borrowings | C7: 27965 | D7: 23545 | E7: 31528 | F7: 37429 | G7: 64436 | H7: 93786 | I7: 88128 | J7: 78606 | K7: 130790 | L7: 101910 | M7: 110631 | N7: 103670
B8: Lease Liabilities | C8: 0 | D8: 0 | E8: 0 | F8: 0 | G8: 0 | H8: 0 | I8: 8314 | J8: 15669 | K8: 20426 | L8: 21520 | M8: 22045 | N8: 23579
B9: Other Borrowings | C9: 12121 | D9: 16212 | E9: 13662 | F9: 38029 | G9: 16933 | H9: 44877 | I9: 0 | J9: 0 | K9: 4425 | L9: 4577 | M9: 4738 | N9: 4962
B10: Other Liabilities - | C10: 117736 | D10: 172727 | E10: 225618 | F10: 277924 | G10: 302804 | H10: 358716 | I10: 340931 | J10: 399979 | K10: 438346 | L10: 610848 | M10: 732200 | N10: 870554
B11: Non controlling int | C11: 3038 | D11: 3356 | E11: 2917 | F11: 3539 | G11: 8280 | H11: 12181 | I11: 99260 | J11: 109499 | K11: 113009 | L11: 132307 | M11: 166426 | N11: 181836
B12: Trade Payables | C12: 59407 | D12: 60296 | E12: 76595 | F12: 106861 | G12: 108309 | H12: 96799 | I12: 108897 | J12: 159330 | K12: 147172 | L12: 178377 | M12: 186789 | N12: 158842
B13: Other liability items | C13: 55291 | D13: 109075 | E13: 146106 | F13: 167524 | G13: 186215 | H13: 249736 | I13: 132774 | J13: 131150 | K13: 178165 | L13: 300164 | M13: 378985 | N13: 529876
... B36: Total Assets | C36: 504486 | D36: 598997 | E36: 706802 | F36: 811273 | G36: 997630 | H36: 1163015 | I36: 1320065 | J36: 1498622 | K36: 1605882 | L36: 1755048 | M36: 1949713 | N36: 2177546
C39: 42064 | D39: 42430 | E39: 42795 | F39: 43160 | G39: 43525 | H39: 43891 | I39: 44256 | J39: 44621 | K39: 44986 | L39: 45352 | M39: 45717 | N39: 46082
B40: Cash from Operating Activity - | C40: 34374 | D40: 38134 | E40: 49550 | F40: 71459 | G40: 42346 | H40: 94877 | I40: 26958 | J40: 110654 | K40: 115032 | L40: 158788 | M40: 178703 | N40: 192113
B41: Profit from operations | C41: 38994 | D41: 38887 | E41: 44170 | F41: 62765 | G41: 83319 | H41: 85347 | I41: 80129 | J41: 113726 | K41: 140963 | L41: 164383 | M41: 166904 | N41: 189224
B42: Receivables | C42: 1097 | D42: -6880 | E42: -8511 | F42: -21991 | G42: -40136 | H42: -13792 | I42: 959 | J42: -14180 | K42: 13194 | L42: -15674 | M42: -17837 | N42: -53322
B43: Inventory | C43: 3472 | D43: 6758 | E43: -6899 | F43: -10474 | G43: -6724 | H43: -6342 | I43: -7769 | J43: -24983 | K43: -32228 | L43: -12756 | M43: 3134 | N43: -20790
B44: Payables | C44: -2754 | D44: 7951 | E44: 30873 | F44: 51003 | G44: 18078 | H44: 38050 | I44: -43148 | J44: 39888 | K44: -600 | L44: 34796 | M44: 38427 | N44: 86609
B45: Working capital changes | C45: 1815 | D45: 7829 | E45: 15463 | F45: 18538 | G45: -28782 | H45: 17916 | I45: -49958 | J45: 725 | K45: -19634 | L45: 6366 | M45: 23724 | N45: 12497
B46: Direct taxes | C46: -6435 | D46: -8582 | E46: -10083 | F46: -9844 | G46: -12191 | H46: -8386 | I46: -3213 | J46: -3797 | K46: -6297 | L46: -11961 | M46: -11925 | N46: -9608
B47: Cash from Investing Activity - | C47: -64706 | D47: -36186 | E47: -66201 | F47: -68192 | G47: -94507 | H47: -72497 | I47: -142385 | J47: -109162 | K47: -93001 | L47: -113581 | M47: -137535 | N47: -101089
B48: Fixed assets purchased | C48: -63364 | D48: -46898 | E48: -78109 | F48: -73953 | G48: -93626 | H48: -76517 | I48: -105837 | J48: -100145 | K48: -140988 | L48: -152883 | M48: -139967 | N48: -122916
B49: Fixed assets sold | C49: 402 | D49: 344 | E49: 1482 | F49: 999 | G49: 849 | H49: 964 | I49: 2319 | J49: 3137 | K49: 9186 | L49: 15307 | M49: 2343 | N49: 826
B50: Investments purchased | C50: -678241 | D50: -715334 | E50: -654760 | F50: -533984 | G50: -1107439 | H50: -1156843 | I50: -689866 | J50: -667878 | K50: -471822 | L50: -513660 | M50: -684340 | N50: -988777
B51: Investments sold | C51: 666383 | D51: 721182 | E51: 663990 | F51: 537504 | G51: 1103615 | H51: 1174796 | I51: 642551 | J51: 668137 | K51: 501266 | L51: 531355 | M51: 672558 | N51: 991876
... B66: CFO/OP | C66: 1.09 | D66: 1.12 | E66: 1.29 | F66: 1.26 | G66: 0.65 | H66: 1.16 | I66: 0.37 | J66: 1.05 | K66: 0.85 | L66: 1.05 | M66: 1.15 | N66: 1.13

Sheet DCF>>
B3: Calculation of PV of FCFF | D3: ='intrinsic Growth'!L8 -> 46082 | E3: =D3+366 -> 46448 | F3: =E3+365 -> 46813 | G3: =F3+365 -> 47178 | H3: =G3+365 -> 47543 | I3: =H3+365 -> 47908
B5: EBIT | D5: =HistoricalFS!L52+HistoricalFS!L49+HistoricalFS!L43 -> 150223 | E5: =D5*(1+$C$15) -> 160738.61 | F5: =E5*(1+$C$15) -> 171990.31 | G5: =F5*(1+$C$15) -> 184029.63 | H5: =G5*(1+$C$15) -> 196911.71 | I5: =H5*(1+$C$15) -> 210695.53
B6: Tax Rate | D6: 0.25 | E6: =D6 -> 0.25 | F6: =E6 -> 0.25 | G6: =F6 -> 0.25 | H6: =G6 -> 0.25 | I6: =H6 -> 0.25
B7: EBIT(1-Tax Rate) | D7: =D5*(1-D6) -> 112667.25 | E7: =E5*(1-E6) -> 120553.96 | F7: =F5*(1-F6) -> 128992.73 | G7: =G5*(1-G6) -> 138022.23 | H7: =H5*(1-H6) -> 147683.78 | I7: =I5*(1-I6) -> 158021.65
B8: Less: Reinvestment Rate | D8: 0.8 | E8: =D8 -> 0.8 | F8: =E8 -> 0.8 | G8: =F8 -> 0.8 | H8: =G8 -> 0.8 | I8: =H8 -> 0.8
B9: Free Cash Flow to Firm (FCFF) | D9: =D7*(1-D8) -> 22533.45 | E9: =E7*(1-E8) -> 24110.791 | F9: =F7*(1-F8) -> 25798.547 | G9: =G7*(1-G8) -> 27604.445 | H9: =H7*(1-H8) -> 29536.756 | I9: =I7*(1-I8) -> 31604.329
B10: Mid Year Convention | E10: 0.5 | F10: =E10+1 -> 1.5 | G10: =F10+1 -> 2.5 | H10: =G10+1 -> 3.5 | I10: =H10+1 -> 4.5
B11: Discount Factor | E11: =1/(1+$C$17)^E10 -> 0.93838446 | F11: =1/(1+$C$17)^F10 -> 0.82630888 | G11: =1/(1+$C$17)^G10 -> 0.727619 | H11: =1/(1+$C$17)^H10 -> 0.64071611 | I11: =1/(1+$C$17)^I10 -> 0.56419243
B12: PV of FCFF | E12: =E9*E11 -> 22625.192 | F12: =F9*F11 -> 21317.568 | G12: =G9*G11 -> 20085.519 | H12: =H9*H11 -> 18924.676 | I12: =I9*I11 -> 17830.923
B15: Expected Growth Rate | C15: 0.07
B16: Terminal Growth Rate | C16: 0.058
B17: WACC | C17: =WACC!J47 -> 0.135634
B19: Calculation of Terminal Value
B21: FCFF (n+1) | C21: =I9*(1+C15) -> 33816.632
B22: WACC | C22: =C17 -> 0.135634
B23: Terminal Growth Rate | C23: =C16 -> 0.058
B24: Terminal Value | C24: =C21/(C22-C23) -> 435590.47
B26: Calculation of Equity Value per Share
B28: PV of FCFF | C28: =SUM(E12:I12) -> 100783.88
B29: PV of Terminal value | C29: =C24 -> 435590.47
B30: Value of Operating Assets | C30: =SUM(C28:C29) -> 536374.35
B32: Add: Cash | C32: =HistoricalFS!L82 -> 145977
B33: Less: Debt | C33: =SUM(RawFs!N6:N7) -> 374421
B34: Value of Equity | C34: =(C30+C32)-C33 -> 307930.35
B35: No of Share | C35: ='Data Sheet '!B7 -> 1353.8808
B36: Equity Value Per Share | C36: =C34/C35 -> 227.44273
B38: Share Price | C38: 1198
B39: Discount/Premium | C39: =C38/C36 -> 5.26726

Sheet Sectorwise Data
B3: India - Sector Data
B4: Figures in $mn
B5: Industry Name | C5: Number of Firms | D5: Capital Expenditures | E5: Depreciation & Amort | F5: CapEx/Deprecn | G5: Acquisitions | H5: Net R&D | I5: Net Cap Ex/Sales | J5: Net Cap Ex/ EBIT (1-t) | K5: Sales/ Invested Capital | L5: Reinvestment Rate | M5: Expected EBIT Growth
B6: Advertising | C6: 13 | D6: 12.255 | E6: 6.172 | F6: 1.98558 | G6: 15.7 | H6: 1.95 | I6: 0.11509867 | J6: 0.92871968 | K6: 4.3520758 | L6: =1/K6 -> 0.22977541 | M6: =VLOOKUP(B6,'[1]Industry Averages'!$A$9:$E$104,5,0) -> 0.58596196
B7: Aerospace/Defense | C7: 13 | D7: 179.856 | E7: 230.043 | F7: 0.78183644 | G7: 0 | H7: 130.9138 | I7: 0.011286263 | J7: 0.085900571 | K7: 2.3987362 | L7: =1/K7 -> 0.4168862 | M7: =VLOOKUP(B7,'[1]Industry Averages'!$A$9:$E$104,5,0) -> 0.03398414
B8: Air Transport | C8: 6 | D8: 522.139 | E8: 907.273 | F8: 0.57550373 | G8: 0 | H8: 0 | I8: -0.052425789 | J8: -30.163963 | K8: 0.99250582 | L8: =1/K8 -> 1.0075508 | M8: =VLOOKUP(B8,'[1]Industry Averages'!$A$9:$E$104,5,0) -> -0.5981078
B9: Apparel | C9: 323 | D9: 1319.155 | E9: 1037.401 | F9: 1.271596 | G9: 18.023 | H9: 19.954 | I9: 0.0044862222 | J9: 0.13248117 | K9: 2.8247624 | L9: =1/K9 -> 0.35401208 | M9: =VLOOKUP(B9,'[1]Industry Averages'!$A$9:$E$104,5,0) -> 0.0951539
B10: Auto & Truck | C10: 12 | D10: 2055.735 | E10: 4078.638 | F10: 0.50402487 | G10: 103.4 | H10: 106.7262 | I10: -0.023678848 | J10: -0.48880652 | K10: 1.1695525 | L10: =1/K10 -> 0.85502786 | M10: =VLOOKUP(B10,'[1]Industry Averages'!$A$9:$E$104,5,0) -> -0.035019143
B11: Auto Parts | C11: 107 | D11: 1610.951 | E11: 1354.436 | F11: 1.1893888 | G11: 188.833 | H11: 14.6402 | I11: 0.012636963 | J11: 0.25411286 | K11: 1.9351197 | L11: =1/K11 -> 0.51676391 | M11: =VLOOKUP(B11,'[1]Industry Averages'!$A$9:$E$104,5,0) -> 0.05925667
B12: Bank (Money Center) | C12: 32 | D12: 2515.32 | E12: 9.25 | F12: NA | G12: 283.761 | H12: 0 | I12: 0.028561625 | J12: 95.335947 | K12: 0.43746869 | L12: =1/K12 -> 2.2858779 | M12: =VLOOKUP(B12,'[1]Industry Averages'!$A$9:$E$104,5,0) -> 0.011761751
B13: Banks (Regional) | C13: 5 | D13: 90.31 | E13: 0 | F13: NA | G13: 0 | H13: 0 | I13: 0.04048142 | J13: 14.611621 | K13: 0.52508707 | L13: =1/K13 -> 1.904446 | M13: =VLOOKUP(B13,'[1]Industry Averages'!$A$9:$E$104,5,0) -> 0.021963454
B14: Beverage (Alcoholic) | C14: 19 | D14: 132.855 | E14: 94.074 | F14: 1.4122393 | G14: 31.03 | H14: 1.323 | I14: 0.01977449 | J14: 0.23780071 | K14: 1.8773559 | L14: =1/K14 -> 0.53266405 | M14: =VLOOKUP(B14,'[1]Industry Averages'!$A$9:$E$104,5,0) -> 0.043070541
B15: Beverage (Soft) | C15: 5 | D15: 1.59 | E15: 70.091 | F15: 0.022684795 | G15: 0 | H15: 0 | I15: -0.043484802 | J15: -0.34007574 | K15: 2.003551 | L15: =1/K15 -> 0.49911381 | M15: =VLOOKUP(B15,'[1]Industry Averages'!$A$9:$E$104,5,0) -> -0.10415247
B16: Broadcasting | C16: 17 | D16: 182.505 | E16: 165.614 | F16: 1.1019902 | G16: 4.95 | H16: 0.0408 | I16: 0.0064843801 | J16: 0.04850055 | K16: 1.0879531 | L16: =1/K16 -> 0.91915728 | M16: =VLOOKUP(B16,'[1]Industry Averages'!$A$9:$E$104,5,0) -> 0.17417748
B17: Brokerage & Investment Banking | C17: 174 | D17: 98.346 | E17: 60.774 | F17: 1.6182249 | G17: 1.609 | H17: 0.9788 | I17: 0.0057186927 | J17: 2.605898 | K17: 0.79574458 | L17: =1/K17 -> 1.2566847 | M17: =VLOOKUP(B17,'[1]Industry Averages'!$A$9:$E$104,5,0) -> 0.01122989
B18: Building Materials | C18: 48 | D18: 294.063 | E18: 132.09 | F18: 2.2262321 | G18: -0.027 | H18: 0.4822 | I18: 0.030565549 | J18: 0.55016619 | K18: 2.0105272 | L18: =1/K18 -> 0.49738198 | M18: =VLOOKUP(B18,'[1]Industry Averages'!$A$9:$E$104,5,0) -> 0.17157185
B19: Business & Consumer Services | C19: 58 | D19: 141.797 | E19: 125.523 | F19: 1.1296495 | G19: -26.311 | H19: 0.0796 | I19: -0.0015559104 | J19: -0.022128622 | K19: 4.0759056 | L19: =1/K19 -> 0.24534425 | M19: =VLOOKUP(B19,'[1]Industry Averages'!$A$9:$E$104,5,0) -> 0.13481715
B20: Cable TV | C20: 8 | D20: 207.31 | E20: 272.431 | F20: 0.76096333 | G20: -0.428 | H20: 0 | I20: -0.050339982 | J20: -0.91369891 | K20: 0.98018147 | L20: =1/K20 -> 1.0202192 | M20: =VLOOKUP(B20,'[1]Industry Averages'!$A$9:$E$104,5,0) -> -0.0035265426
B21: Chemical (Basic) | C21: 128 | D21: 1638.433 | E21: 741.087 | F21: 2.2108511 | G21: 29.028 | H21: 4.4914 | I21: 0.036515056 | J21: 0.36157794 | K21: 1.4829761 | L21: =1/K21 -> 0.67431971 | M21: =VLOOKUP(B21,'[1]Industry Averages'!$A$9:$E$104,5,0) -> 0.11908759
B22: Chemical (Diversified) | C22: 10 | D22: 678.43 | E22: 188.1 | F22: 3.6067517 | G22: 33.42 | H22: 1.6744 | I22: 0.068788133 | J22: 0.69803449 | K22: 1.9394418 | L22: =1/K22 -> 0.51561227 | M22: =VLOOKUP(B22,'[1]Industry Averages'!$A$9:$E$104,5,0) -> 0.22137522
B23: Chemical (Specialty) | C23: 167 | D23: 2136.228 | E23: 1159.721 | F23: 1.8420189 | G23: 149.754 | H23: -8.0284 | I23: 0.022489218 | J23: 0.23451832 | K23: 2.0349819 | L23: =1/K23 -> 0.49140486 | M23: =VLOOKUP(B23,'[1]Industry Averages'!$A$9:$E$104,5,0) -> 0.20753919
B24: Coal & Related Energy | C24: 2 | D24: 1808.8 | E24: 550.3 | F24: 3.2869344 | G24: 0 | H24: 0.786 | I24: 0.082890845 | J24: 0.43299618 | K24: 4.0386197 | L24: =1/K24 -> 0.24760935 | M24: =VLOOKUP(B24,'[1]Industry Averages'!$A$9:$E$104,5,0) -> 0.29707528
B25: Computer Services | C25: 132 | D25: 1553.518 | E25: 2311.906 | F25: 0.67196417 | G25: 1856.958 | H25: -15.5838 | I25: 0.011830691 | J25: 0.089775144 | K25: 2.3636029 | L25: =1/K25 -> 0.42308292 | M25: =VLOOKUP(B25,'[1]Industry Averages'!$A$9:$E$104,5,0) -> 0.13864804
... B30: Drugs (Pharmaceutical) | C30: 156 | D30: 2186.779 | E30: 1565.338 | F30: 1.3970012 | G30: 407.009 | H30: 93.1694 | I30: 0.031780616 | J30: 0.29197519 | K30: 0.9289109 | L30: =1/K30 -> 1.0765295 | M30: =VLOOKUP(B30,'[1]Industry Averages'!$A$9:$E$104,5,0) -> 0.0549422
B31: Education | C31: 26 | D31: 9.189 | E31: 17.787 | F31: 0.51661326 | G31: 4.209 | H31: 0.3008 | I31: -0.025667073 | J31: NA | K31: 0.46552026 | L31: =1/K31 -> 2.1481342 | M31: =VLOOKUP(B31,'[1]Industry Averages'!$A$9:$E$104,5,0) -> NA
B32: Electrical Equipment | C32: 102 | D32: 563.663 | E32: 356.551 | F32: 1.5808762 | G32: 1.613 | H32: 32.2512 | I32: 0.013219963 | J32: 0.28987967 | K32: 1.5318774 | L32: =1/K32 -> 0.65279376 | M32: =VLOOKUP(B32,'[1]Industry Averages'!$A$9:$E$104,5,0) -> 0.054779301
B33: Electronics (Consumer & Office) | C33: 8 | D33: 57.396 | E33: 14.183 | F33: 4.0468166 | G33: 0 | H33: 0.4182 | I33: 0.02488621 | J33: 1.2335302 | K33: 8.0284903 | L33: =1/K33 -> 0.12455642 | M33: =VLOOKUP(B33,'[1]Industry Averages'!$A$9:$E$104,5,0) -> 0.3261852
B34: Electronics (General) | C34: 27 | D34: 56.801 | E34: 29.397 | F34: 1.932204 | G34: 38.2 | H34: 1.4602 | I34: 0.04877407 | J34: 0.76100466 | K34: 2.4268056 | L34: =1/K34 -> 0.41206432 | M34: =VLOOKUP(B34,'[1]Industry Averages'!$A$9:$E$104,5,0) -> 0.27119359
B35: Engineering/Construction | C35: 144 | D35: 1658.835 | E35: 1125.749 | F35: 1.473539 | G35: 31.045 | H35: 41.3822 | I35: 0.01222911 | J35: 0.18999347 | K35: 0.97947461 | L35: =1/K35 -> 1.0209555 | M35: =VLOOKUP(B35,'[1]Industry Averages'!$A$9:$E$104,5,0) -> 0.048665675
B36: Entertainment | C36: 60 | D36: 108.201 | E36: 238.994 | F36: 0.45273522 | G36: 14.456 | H36: 0.227 | I36: -0.063295763 | J36: -0.90136254 | K36: 0.67995091 | L36: =1/K36 -> 1.4706944 | M36: =VLOOKUP(B36,'[1]Industry Averages'!$A$9:$E$104,5,0) -> 0.0066039227
B37: Environmental & Waste Services | C37: 10 | D37: 37.591 | E37: 8.302 | F37: 4.5279451 | G37: 0 | H37: 0.1204 | I37: 0.047153118 | J37: 0.31870481 | K37: 5.2712447 | L37: =1/K37 -> 0.18970851 | M37: =VLOOKUP(B37,'[1]Industry Averages'!$A$9:$E$104,5,0) -> 0.84345977
B38: Farming/Agriculture | C38: 57 | D38: 161.962 | E38: 119.337 | F38: 1.3571818 | G38: -3.786 | H38: 2.4352 | I38: 0.0077462768 | J38: 0.13946671 | K38: 1.4992995 | L38: =1/K38 -> 0.66697815 | M38: =VLOOKUP(B38,'[1]Industry Averages'!$A$9:$E$104,5,0) -> 0.041177374
B39: Financial Svcs. (Non-bank & Insurance) | C39: 254 | D39: 906.479 | E39: 620.979 | F39: 1.4597579 | G39: 287.916 | H39: 0.3624 | I39: 0.011353578 | J39: 0.1942699 | K39: 0.10361554 | L39: =1/K39 -> 9.6510623 | M39: =VLOOKUP(B39,'[1]Industry Averages'!$A$9:$E$104,5,0) -> 0.0016319973
B40: Food Processing | C40: 185 | D40: 1139.239 | E40: 609.472 | F40: 1.8692229 | G40: 99.593 | H40: 3.0956 | I40: 0.016544828 | J40: 0.34667722 | K40: 2.3987394 | L40: =1/K40 -> 0.41688564 | M40: =VLOOKUP(B40,'[1]Industry Averages'!$A$9:$E$104,5,0) -> 0.054777163
B41: Food Wholesalers | C41: 32 | D41: 6.987 | E41: 5.029 | F41: 1.3893418 | G41: 0 | H41: 0.0144 | I41: 0.0019393916 | J41: 0.27852798 | K41: 6.2547509 | L41: =1/K41 -> 0.15987847 | M41: =VLOOKUP(B41,'[1]Industry Averages'!$A$9:$E$104,5,0) -> -0.12880592
B42: Furn/Home Furnishings | C42: 38 | D42: 205.164 | E42: 125.409 | F42: 1.6359591 | G42: 258.564 | H42: 0.717 | I42: 0.056785498 | J42: 1.2293977 | K42: 2.8429462 | L42: =1/K42 -> 0.35174777 | M42: =VLOOKUP(B42,'[1]Industry Averages'!$A$9:$E$104,5,0) -> 0.16055102
B43: Green & Renewable Energy | C43: 18 | D43: 2209.946 | E43: 407.417 | F43: 5.4242852 | G43: 155.484 | H43: 0.0186 | I43: 0.62222232 | J43: 1.7375867 | K43: 0.17791576 | L43: =1/K43 -> 5.6206375 | M43: =VLOOKUP(B43,'[1]Industry Averages'!$A$9:$E$104,5,0) -> 0.1203388
... B46: Heathcare Information and Technology | C46: 14 | D46: 245.562 | E46: 130.381 | F46: 1.8834186 | G46: 0 | H46: -5.9586 | I46: 0.052776096 | J46: 0.27452649 | K46: 0.84191312 | L46: =1/K46 -> 1.187771 | M46: =VLOOKUP(B46,'[1]Industry Averages'!$A$9:$E$104,5,0) -> 0.068925326
B47: Homebuilding | C47: 1 | D47: 0 | E47: 0 | F47: NA | G47: 0 | H47: 0 | I47: 0 | J47: 0 | K47: 0.39187228 | L47: =1/K47 -> 2.5518519 | M47: =VLOOKUP(B47,'[1]Industry Averages'!$A$9:$E$104,5,0) -> -0.087953556
B48: Hospitals/Healthcare Facilities | C48: 24 | D48: 359.256 | E48: 253.77 | F48: 1.4156756 | G48: 37.39 | H48: -0.2278 | I48: 0.028952691 | J48: 0.27604457 | K48: 1.5637777 | L48: =1/K48 -> 0.63947707 | M48: =VLOOKUP(B48,'[1]Industry Averages'!$A$9:$E$104,5,0) -> 0.061834622
B49: Hotel/Gaming | C49: 57 | D49: 148.636 | E49: 218.179 | F49: 0.68125713 | G49: 2.832 | H49: -0.2888 | I49: -0.024199395 | J49: -0.28817139 | K49: 0.54590969 | L49: =1/K49 -> 1.8318048 | M49: =VLOOKUP(B49,'[1]Industry Averages'!$A$9:$E$104,5,0) -> -0.01690855
B50: Household Products | C50: 36 | D50: 349.272 | E50: 289.444 | F50: 1.2066997 | G50: 7.234 | H50: 0.2278 | I50: 0.0053128495 | J50: 0.034634032 | K50: 1.8467134 | L50: =1/K50 -> 0.54150255 | M50: =VLOOKUP(B50,'[1]Industry Averages'!$A$9:$E$104,5,0) -> 0.049129456
B51: Information Services | C51: 24 | D51: 242.605 | E51: 190.988 | F51: 1.2702631 | G51: 152.813 | H51: 0.8042 | I51: 0.054409208 | J51: NA | K51: 2.0161587 | L51: =1/K51 -> 0.49599271 | M51: =VLOOKUP(B51,'[1]Industry Averages'!$A$9:$E$104,5,0) -> NA
B52: Insurance (General) | C52: 2 | D52: 22.01 | E52: 20.84 | F52: 1.056142 | G52: 0 | H52: 0 | I52: 0.00059022348 | J52: NA | K52: 2.0227551 | L52: =1/K52 -> 0.49437522 | M52: =VLOOKUP(B52,'[1]Industry Averages'!$A$9:$E$104,5,0) -> NA
B53: Insurance (Life) | C53: 7 | D53: 159.36 | E53: -1789.213 | F53: NA | G53: 0 | H53: 0 | I53: 0.015894366 | J53: 1.0830439 | K53: 27.659866 | L53: =1/K53 -> 0.036153465 | M53: =VLOOKUP(B53,'[1]Industry Averages'!$A$9:$E$104,5,0) -> 0.52271366
B54: Insurance (Prop/Cas.) | C54: 2 | D54: 20.02 | E54: 7.8 | F54: 2.5666667 | G54: 0 | H54: 0 | I54: 0.0017839156 | J54: 0.023687101 | K54: 1.1971136 | L54: =1/K54 -> 0.83534263 | M54: =VLOOKUP(B54,'[1]Industry Averages'!$A$9:$E$104,5,0) -> 0.0021071216
B55: Investments & Asset Management | C55: 96 | D55: 123.974 | E55: 152.524 | F55: 0.81281634 | G55: 0.014 | H55: 0.798 | I55: -0.0062420506 | J55: -0.032318518 | K55: 0.23998448 | L55: =1/K55 -> 4.1669362 | M55: =VLOOKUP(B55,'[1]Industry Averages'!$A$9:$E$104,5,0) -> -0.0091890334
B56: Machinery | C56: 149 | D56: 364.846 | E56: 282.71 | F56: 1.2905309 | G56: 47.929 | H56: -203.9688 | I56: -0.0065319395 | J56: -0.081072682 | K56: 1.7491018 | L56: =1/K56 -> 0.57172203 | M56: =VLOOKUP(B56,'[1]Industry Averages'!$A$9:$E$104,5,0) -> 0.057117455
B57: Metals & Mining | C57: 39 | D57: 3290.709 | E57: 2544.546 | F57: 1.2932401 | G57: 50.6 | H57: 2.4316 | I57: 0.015023865 | J57: 0.12188783 | K57: 1.5089391 | L57: =1/K57 -> 0.66271725 | M57: =VLOOKUP(B57,'[1]Industry Averages'!$A$9:$E$104,5,0) -> 0.047486807
B58: Office Equipment & Services | C58: 13 | D58: 11.138 | E58: 8.616 | F58: 1.2927112 | G58: 0 | H58: 0.0434 | I58: 0.010388843 | J58: 0.16317856 | K58: 1.983694 | L58: =1/K58 -> 0.50411001 | M58: =VLOOKUP(B58,'[1]Industry Averages'!$A$9:$E$104,5,0) -> 0.094608582
B59: Oil/Gas (Integrated) | C59: 1 | D59: 5441.3 | E59: 3108.8 | F59: 1.7502895 | G59: 0 | H59: 6.76 | I59: 0.031070945 | J59: 0.44887613 | K59: 1.5854294 | L59: =1/K59 -> 0.63074393 | M59: =VLOOKUP(B59,'[1]Industry Averages'!$A$9:$E$104,5,0) -> 0.039412352
B60: Oil/Gas (Production and Exploration) | C60: 6 | D60: 984.041 | E60: 356.791 | F60: 2.758032 | G60: 0 | H60: 3.4 | I60: 0.12979088 | J60: 0.55508675 | K60: 0.76607136 | L60: =1/K60 -> 1.3053614 | M60: =VLOOKUP(B60,'[1]Industry Averages'!$A$9:$E$104,5,0) -> 0.13604872
B61: Oil/Gas Distribution | C61: 11 | D61: 175.249 | E61: 307.997 | F61: 0.5689958 | G61: 24.6 | H61: 0 | I61: -0.012710918 | J61: -0.13728574 | K61: 2.4712319 | L61: =1/K61 -> 0.40465648 | M61: =VLOOKUP(B61,'[1]Industry Averages'!$A$9:$E$104,5,0) -> 0.051078271
B62: Oilfield Svcs/Equip. | C62: 22 | D62: 20972.774 | E62: 7314.322 | F62: 2.8673572 | G62: 303.3 | H62: 20.5486 | I62: 0.043075722 | J62: 1.2697498 | K62: 1.7169471 | L62: =1/K62 -> 0.58242912 | M62: =VLOOKUP(B62,'[1]Industry Averages'!$A$9:$E$104,5,0) -> 0.14364011
B63: Packaging & Container | C63: 79 | D63: 496.734 | E63: 241.195 | F63: 2.0594706 | G63: -0.021 | H63: 0.7066 | I63: 0.039511584 | J63: 0.69052922 | K63: 1.4785431 | L63: =1/K63 -> 0.67634148 | M63: =VLOOKUP(B63,'[1]Industry Averages'!$A$9:$E$104,5,0) -> 0.12924755
B64: Paper/Forest Products | C64: 50 | D64: 383.407 | E64: 200.152 | F64: 1.9155792 | G64: 6.629 | H64: 0.8082 | I64: 0.035064033 | J64: 0.36737281 | K64: 1.2129511 | L64: =1/K64 -> 0.82443556 | M64: =VLOOKUP(B64,'[1]Industry Averages'!$A$9:$E$104,5,0) -> 0.057808054
B65: Power | C65: 30 | D65: 9577.575 | E65: 6046.038 | F65: 1.5841076 | G65: 136.3 | H65: 11.2516 | I65: 0.049610994 | J65: 0.33518377 | K65: 0.54234524 | L65: =1/K65 -> 1.843844 | M65: =VLOOKUP(B65,'[1]Industry Averages'!$A$9:$E$104,5,0) -> 0.052286629
B66: Precious Metals | C66: 1 | D66: 0.038 | E66: 0.003 | F66: 12.666667 | G66: 0 | H66: 0 | I66: 8.75 | J66: NA | K66: 0.00068622405 | L66: =1/K66 -> 1457.25 | M66: =VLOOKUP(B66,'[1]Industry Averages'!$A$9:$E$104,5,0) -> NA
B67: Publishing & Newspapers | C67: 25 | D67: 22.612 | E67: 66.912 | F67: 0.33793639 | G67: 4.995 | H67: 0.1012 | I67: -0.03145557 | J67: -0.47283571 | K67: 0.79541061 | L67: =1/K67 -> 1.2572123 | M67: =VLOOKUP(B67,'[1]Industry Averages'!$A$9:$E$104,5,0) -> -0.0020872203
B68: R.E.I.T. | C68: 4 | D68: 0.479 | E68: 221.1 | F68: 0.0021664405 | G68: 167.4 | H68: 0 | I68: -0.055450094 | J68: -0.11960151 | K68: 0.10401743 | L68: =1/K68 -> 9.6137737 | M68: =VLOOKUP(B68,'[1]Industry Averages'!$A$9:$E$104,5,0) -> -0.0052557108
B69: Real Estate (Development) | C69: 137 | D69: 458.396 | E69: 132.474 | F69: 3.4602714 | G69: -1.069 | H69: 0.2194 | I69: 0.065727372 | J69: 0.46036074 | K69: 0.35545556 | L69: =1/K69 -> 2.8132912 | M69: =VLOOKUP(B69,'[1]Industry Averages'!$A$9:$E$104,5,0) -> 0.04609447
B70: Real Estate (General/Diversified) | C70: 15 | D70: 43.756 | E70: 91.657 | F70: 0.47738852 | G70: 114.001 | H70: 0.0678 | I70: 0.037157453 | J70: 0.19097827 | K70: 0.18337935 | L70: =1/K70 -> 5.4531766 | M70: =VLOOKUP(B70,'[1]Industry Averages'!$A$9:$E$104,5,0) -> -0.0055160551
B71: Real Estate (Operations & Services) | C71: 30 | D71: 2.449 | E71: 24.22 | F71: 0.10111478 | G71: 0 | H71: 0.0206 | I71: -0.12135807 | J71: -0.35085283 | K71: 0.22237473 | L71: =1/K71 -> 4.4969138 | M71: =VLOOKUP(B71,'[1]Industry Averages'!$A$9:$E$104,5,0) -> -0.032764429
B72: Recreation | C72: 11 | D72: 3.551 | E72: 18.69 | F72: 0.18999465 | G72: 0 | H72: -0.0036 | I72: -0.13896246 | J72: -0.87944318 | K72: 0.39546291 | L72: =1/K72 -> 2.5286821 | M72: =VLOOKUP(B72,'[1]Industry Averages'!$A$9:$E$104,5,0) -> -0.04829848
B73: Reinsurance | C73: 1 | D73: 2.48 | E73: 0.8 | F73: 3.1 | G73: 0 | H73: 0 | I73: 0.00028865483 | J73: 0.0034129116 | K73: 1.0845426 | L73: =1/K73 -> 0.92204773 | M73: =VLOOKUP(B73,'[1]Industry Averages'!$A$9:$E$104,5,0) -> 0.00031305845
B74: Restaurant/Dining | C74: 13 | D74: 238.219 | E74: 197.712 | F74: 1.2048788 | G74: 96.355 | H74: 0 | I74: 0.069807001 | J74: 0.883824 | K74: 1.116234 | L74: =1/K74 -> 0.89586949 | M74: =VLOOKUP(B74,'[1]Industry Averages'!$A$9:$E$104,5,0) -> 0.089699132
B75: Retail (Automotive) | C75: 4 | D75: 2.09 | E75: 2.961 | F75: 0.70584262 | G75: 0 | H75: 0 | I75: -0.0040863817 | J75: -0.29761597 | K75: 3.9132518 | L75: =1/K75 -> 0.25554195 | M75: =VLOOKUP(B75,'[1]Industry Averages'!$A$9:$E$104,5,0) -> 0.11542089
B76: Retail (Building Supply) | C76: 2 | D76: 5.16 | E76: 6.35 | F76: 0.81259843 | G76: 0 | H76: 0 | I76: -0.0027262314 | J76: -0.47387853 | K76: 3.931724 | L76: =1/K76 -> 0.25434135 | M76: =VLOOKUP(B76,'[1]Industry Averages'!$A$9:$E$104,5,0) -> -0.070849813
B77: Retail (Distributors) | C77: 239 | D77: 1877.353 | E77: 270.195 | F77: 6.9481412 | G77: 66.355 | H77: 0.03 | I77: 0.086444958 | J77: 3.0138248 | K77: 1.8495472 | L77: =1/K77 -> 0.54067287 | M77: =VLOOKUP(B77,'[1]Industry Averages'!$A$9:$E$104,5,0) -> 0.13155021
B78: Retail (General) | C78: 5 | D78: 37.17 | E78: 304.18 | F78: 0.12219738 | G78: 0 | H78: 0 | I78: -0.11824019 | J78: NA | K78: 0.78189759 | L78: =1/K78 -> 1.2789399 | M78: =VLOOKUP(B78,'[1]Industry Averages'!$A$9:$E$104,5,0) -> NA
B79: Retail (Grocery and Food) | C79: 5 | D79: 290.518 | E79: 72.546 | F79: 4.004604 | G79: 0 | H79: 0 | I79: 0.044944867 | J79: 0.77377882 | K79: 2.8303328 | L79: =1/K79 -> 0.35331534 | M79: =VLOOKUP(B79,'[1]Industry Averages'!$A$9:$E$104,5,0) -> 0.21158284
B80: Retail (Online) | C80: 13 | D80: 35.311 | E80: 47.831 | F80: 0.73824507 | G80: 26.27 | H80: 0.4292 | I80: 0.0083257489 | J80: NA | K80: 0.90286408 | L80: =1/K80 -> 1.1075864 | M80: =VLOOKUP(B80,'[1]Industry Averages'!$A$9:$E$104,5,0) -> NA
B81: Retail (Special Lines) | C81: 28 | D81: 130.68 | E81: 208.642 | F81: 0.62633602 | G81: -0.12 | H81: 0.1358 | I81: -0.016713977 | J81: -0.73826199 | K81: 1.5681995 | L81: =1/K81 -> 0.63767397 | M81: =VLOOKUP(B81,'[1]Industry Averages'!$A$9:$E$104,5,0) -> 0.069002525
B82: Rubber& Tires | C82: 16 | D82: 867.078 | E82: 510.808 | F82: 1.6974636 | G82: 0 | H82: 2.4634 | I82: 0.034196273 | J82: 0.85892675 | K82: 1.3204629 | L82: =1/K82 -> 0.75731021 | M82: =VLOOKUP(B82,'[1]Industry Averages'!$A$9:$E$104,5,0) -> 0.10110434
B83: Semiconductor | C83: 8 | D83: 11.166 | E83: 3.6 | F83: 3.1016667 | G83: 0 | H83: 0.0512 | I83: 0.098898987 | J83: 6.4894376 | K83: 0.90745 | L83: =1/K83 -> 1.1019891 | M83: =VLOOKUP(B83,'[1]Industry Averages'!$A$9:$E$104,5,0) -> 0.15848688
B84: Semiconductor Equip | C84: 1 | D84: 59.9 | E84: 5.22 | F84: 11.475096 | G84: 0 | H84: 0 | I84: 0.64481132 | J84: 3.190752 | K84: 0.8445374 | L84: =1/K84 -> 1.1840802 | M84: =VLOOKUP(B84,'[1]Industry Averages'!$A$9:$E$104,5,0) -> 0.63668957
B85: Shipbuilding & Marine | C85: 20 | D85: 931.372 | E85: 501.197 | F85: 1.8582952 | G85: 186.8 | H85: 0 | I85: 0.16691159 | J85: 0.53795638 | K85: 0.33701842 | L85: =1/K85 -> 2.9671969 | M85: =VLOOKUP(B85,'[1]Industry Averages'!$A$9:$E$104,5,0) -> 0.053748695
B86: Shoe | C86: 12 | D86: 59.264 | E86: 69.007 | F86: 0.85881142 | G86: -0.001 | H86: 0.3938 | I86: -0.0071880934 | J86: -0.08546306 | K86: 1.6084227 | L86: =1/K86 -> 0.6217271 | M86: =VLOOKUP(B86,'[1]Industry Averages'!$A$9:$E$104,5,0) -> 0.11401249
B87: Software (Entertainment) | C87: 7 | D87: 10.95 | E87: 48.874 | F87: 0.2240455 | G87: 12.31 | H87: 1.2372 | I87: -0.019746166 | J87: -0.1266317 | K87: 0.34598691 | L87: =1/K87 -> 2.8902828 | M87: =VLOOKUP(B87,'[1]Industry Averages'!$A$9:$E$104,5,0) -> 0.02411778
B88: Software (Internet) | C88: 7 | D88: 2.84 | E88: 2.612 | F88: 1.0872894 | G88: 0 | H88: 0 | I88: 0.0070634158 | J88: 0.044442976 | K88: 2.8522577 | L88: =1/K88 -> 0.35059946 | M88: =VLOOKUP(B88,'[1]Industry Averages'!$A$9:$E$104,5,0) -> -0.036861834
B89: Software (System & Application) | C89: 74 | D89: 144.428 | E89: 159.714 | F89: 0.90429142 | G89: 196.192 | H89: 32.9152 | I89: 0.044408639 | J89: 0.35783811 | K89: 1.7224831 | L89: =1/K89 -> 0.58055721 | M89: =VLOOKUP(B89,'[1]Industry Averages'!$A$9:$E$104,5,0) -> 0.16585904
B90: Steel | C90: 157 | D90: 6002.259 | E90: 3615.021 | F90: 1.6603663 | G90: 1294.383 | H90: 53.6032 | I90: 0.035892632 | J90: 0.38824088 | K90: 1.4225481 | L90: =1/K90 -> 0.70296391 | M90: =VLOOKUP(B90,'[1]Industry Averages'!$A$9:$E$104,5,0) -> 0.10464826
B91: Telecom (Wireless) | C91: 3 | D91: 3793.33 | E91: 7141.8 | F91: 0.53114481 | G91: 0 | H91: 0 | I91: -0.15952388 | J91: -1.8400342 | K91: 0.40842598 | L91: =1/K91 -> 2.448424 | M91: =VLOOKUP(B91,'[1]Industry Averages'!$A$9:$E$104,5,0) -> -0.12187765
B92: Telecom. Equipment | C92: 20 | D92: 99.475 | E92: 74.325 | F92: 1.3383787 | G92: 29.494 | H92: 12.5394 | I92: 0.042849453 | J92: 8.5530831 | K92: 0.7211393 | L92: =1/K92 -> 1.3866946 | M92: =VLOOKUP(B92,'[1]Industry Averages'!$A$9:$E$104,5,0) -> 0.41266933
... B97: Trucking | C97: 12 | D97: 39.139 | E97: 24.735 | F97: 1.5823327 | G97: 0 | H97: 0 | I97: 0.023913404 | J97: 0.39030082 | K97: 2.4414306 | L97: =1/K97 -> 0.40959591 | M97: =VLOOKUP(B97,'[1]Industry Averages'!$A$9:$E$104,5,0) -> 0.099366887
B98: Utility (General) | C98: 0 | D98: 0 | E98: 0 | F98: NA | G98: 0 | H98: 0 | I98: NA | J98: NA | K98: NA | L98: =1/K98 -> #VALUE! | M98: =VLOOKUP(B98,'[1]Industry Averages'!$A$9:$E$104,5,0) -> NA
B99: Utility (Water) | C99: 1 | D99: 0.331 | E99: 1.15 | F99: 0.28782609 | G99: 0 | H99: 1.262 | I99: 0.0011937483 | J99: 0.021168747 | K99: 1.5152258 | L99: =1/K99 -> 0.65996766 | M99: =VLOOKUP(B99,'[1]Industry Averages'!$A$9:$E$104,5,0) -> 0.15376352
B100: Total Market | C100: 4149 | D100: 91128.196 | E100: 56787.85 | F100: 1.6047129 | G100: 7200.638 | H100: 290.6888 | I100: 0.024042223 | J100: 0.35915811 | K100: 0.92986384 | L100: =1/K100 -> 1.0754263 | M100: =VLOOKUP(B100,'[1]Industry Averages'!$A$9:$E$104,5,0) -> 0.045696556
B101: Total Market (without financials) | C101: 3577 | D101: 87192.377 | E101: 57704.896 | F101: 1.5110048 | G101: 6627.338 | H101: 288.5496 | I101: 0.025165027 | J101: 0.32789454 | K101: 1.2945772 | L101: =1/K101 -> 0.77245299 | M101: =VLOOKUP(B101,'[1]Industry Averages'!$A$9:$E$104,5,0) -> 0.070760858

Sheet WACC
B4: Weight Average Cost of Capital
B6: All figures are in INR unless stated otherwise
B8: Peer Comps
G9: Debt/ | H9: Debt/ | I9: Levered | J9: Unlevered
B10: Name | C10: Country | D10: Total Debt | E10: Total Equity | F10: Tax Rate1 | G10: Equity | H10: Capital | I10: Beta2 | J10: Beta3
B13: Reliance Industries | C13: India | D13: 402962 | E13: 1659361 | F13: 0.3 | G13: =D13/E13 -> 0.24284167 | H13: =D13/(E13+D13) -> 0.19539228 | I13: ='Beta regressionRL'!K19 -> 0.91951686 | J13: =I13/(1+(1-F13)*G13) -> 0.78591912
B14: Indian Oil Corporation Ltd (IOC) | C14: India | D14: 131822.39 | E14: 192288.42 | F14: 0.3 | G14: =D14/E14 -> 0.68554513 | H14: =D14/(E14+D14) -> 0.40672013 | I14: ='Beta regressionRL'!K76 -> 1.2409791 | J14: =I14/(1+(1-F14)*G14) -> 0.83856652
B15: Bharat Petroleum Corporation Ltd | C15: India | D15: 54424.42 | E15: 133495.13 | F15: 0.3 | G15: =D15/E15 -> 0.40768843 | H15: =D15/(E15+D15) -> 0.28961553 | I15: ='Beta regressionRL'!K133 -> 1.346983 | J15: =I15/(1+(1-F15)*G15) -> 1.0479243
E17: Average | F17: =AVERAGE(F13:F15) -> 0.3 | G17: =AVERAGE(G13:G15) -> 0.44535841 | H17: =AVERAGE(H13:H15) -> 0.29724265 | I17: =AVERAGE(I13:I15) -> 1.1691597 | J17: =AVERAGE(J13:J15) -> 0.89080332
E18: Median | F18: =MEDIAN(F13:F15) -> 0.3 | G18: =MEDIAN(G13:G15) -> 0.40768843 | H18: =MEDIAN(H13:H15) -> 0.28961553 | I18: =MEDIAN(I13:I15) -> 1.2409791 | J18: =MEDIAN(J13:J15) -> 0.83856652
B22: Cost of Debt | G22: Cost of Equity
B24: Pre - Cost of Debt | E24: =HistoricalFS!L43/HistoricalFS!L70 -> 0.067155216 | G24: Risk Free Rate | J24: 0.0711
B25: Tax Rate | E25: =F17 -> 0.3 | G25: Equity Risk Premium | J25: ='AVG Return'!I8-WACC!J24 -> 0.093392308
B26: After Tax Cost of Debt | E26: =E24*(1-E25) -> 0.047008651 | G26: Levered Beta4 | J26: =J35 -> 1.0778782
G27: Cost of Equity | J27: =J24+(J26*J25) -> 0.17176553
B30: Capital Structure | G30: Leveraged Beta
D32: Current | E32: Target | G32: Comps Median Unlevered Beta | J32: =J18 -> 0.83856652
B33: Total Debt | C33: =D13 -> 402962 | D33: =C33/$C$35 -> 0.19539228 | E33: =H18 -> 0.28961553 | G33: Target Debt / Equity | J33: =E37 -> 0.40768843
B34: Market Capitalization | C34: =E13 -> 1659361 | D34: =C34/$C$35 -> 0.80460772 | E34: =E35-E33 -> 0.71038447 | G34: Tax Rate | J34: =F17 -> 0.3
B35: Total Capitalization | C35: =SUM(C33:C34) -> 2062323 | D35: =SUM(D33:D34) -> 1 | E35: =D35 -> 1 | G35: Levered Beta | J35: =J32*(1+(1-J34)*J33) -> 1.0778782
B37: Debt/Equity | D37: =D33/D34 -> 0.24284167 | E37: =E33/E34 -> 0.40768843
G39: Weighted Average Cost of Capital
G41: Cost of Capital | J41: =J27 -> 0.17176553
G42: Equity Weight | J42: =E34 -> 0.71038447
G44: Cost of Debt | J44: =E26 -> 0.047008651
G45: Debt Weight | J45: =E33 -> 0.28961553
G47: WACC | J47: =(J41*J42)+(J44*J45) -> 0.135634

Sheet Comps
B4: S.No. | C4: Company | D4: CMP Rs. | E4: Debt Rs.Cr. | F4: Mar Cap Rs.Cr. | G4: Debt / Eq
B5: 1 | C5: Reliance Industries | D5: 1226 | E5: 402962 | F5: 1659361 | G5: 0.45
B6: 2 | C6: I O C L | D6: 135.7 | E6: 131822.39 | F6: 192288.42 | G6: 0.6
B7: 3 | C7: B P C L | D7: 308.5 | E7: 54424.42 | F7: 133495.13 | G7: 0.54
B8: 4 | C8: H P C L | D8: 351 | E8: 55964.43 | F8: 74569.52 | G8: 0.85
B9: 5 | C9: M R P L | D9: 164.6 | E9: 15341.03 | F9: 28872.35 | G9: 1.08
B10: 6 | C10: C P C L | D10: 1376.4 | E10: 1964.16 | F10: 20486.47 | G10: 0.18

Sheet Beta regressionRL
B4: Reliance Industries Ltd | F4: Nifty 50 Return | J4: Beta Calulation
B6: Date | C6: Closing Price | D6: Return | F6: Date | G6: Closing Price | H6: Return
B7: 45928 | C7: 1363.4 | F7: 45928 | G7: 24894.25 | J7: Beta 1 (Slope) | K7: =SLOPE(D8:D58,H8:H58) -> 0.89268915
B8: 45935 | C8: 1381.7 | D8: =C8/C7-1 -> 0.013422327 | F8: 45935 | G8: 25285.35 | H8: =G8/G7-1 -> 0.015710455 | J8: Beta 2 (Covariance) | K8: {=_xlfn.COVARIANCE.S(D8:D58,H8:H58/_xlfn.VAR.S(H8:H58))} -> 0.89268915
B9: 45942 | C9: 1416.8 | D9: =C9/C8-1 -> 0.025403488 | F9: 45942 | G9: 25709.85 | H9: =G9/G8-1 -> 0.016788377 | J9: Beta 2 (Linear Regression) | K9: =K38 -> 0.89268915
B10: 45949 | C10: 1451.6 | D10: =C10/C9-1 -> 0.024562394 | F10: 45949 | G10: 25795.15 | H10: =G10/G9-1 -> 0.0033177945
B11: 45956 | C11: 1486.4 | D11: =C11/C10-1 -> 0.023973546 | F11: 45956 | G11: 25722.1 | H11: =G11/G10-1 -> -0.0028319277 | J11: Beta Drifting
B12: 45963 | C12: 1478 | D12: =C12/C11-1 -> -0.0056512379 | F12: 45963 | G12: 25492.3 | H12: =G12/G11-1 -> -0.0089339517
B13: 45970 | C13: 1518.9 | D13: =C13/C12-1 -> 0.02767253 | F13: 45970 | G13: 25910.05 | H13: =G13/G12-1 -> 0.016387301 | J13: levered Raw Beta | K13: =K9 -> 0.89268915
B14: 45977 | C14: 1546.6 | D14: =C14/C13-1 -> 0.018236882 | F14: 45977 | G14: 26068.15 | H14: =G14/G13-1 -> 0.0061018794 | J14: Raw Beta Weight | K14: 0.75
B15: 45984 | C15: 1567.5 | D15: =C15/C14-1 -> 0.013513514 | F15: 45984 | G15: 26202.95 | H15: =G15/G14-1 -> 0.0051710612
B16: 45991 | C16: 1540.6 | D16: =C16/C15-1 -> -0.017161085 | F16: 45991 | G16: 26186.45 | H16: =G16/G15-1 -> -0.00062970009 | J16: Market Beta | K16: 1
B17: 45998 | C17: 1556.5 | D17: =C17/C16-1 -> 0.010320654 | F17: 45998 | G17: 26046.95 | H17: =G17/G16-1 -> -0.0053271826 | J17: Market Beta Weight | K17: 0.25
B18: 46005 | C18: 1565.1 | D18: =C18/C17-1 -> 0.0055252168 | F18: 46005 | G18: 25966.4 | H18: =G18/G17-1 -> -0.0030924926
B19: 46012 | C19: 1559.2 | D19: =C19/C18-1 -> -0.0037697272 | F19: 46012 | G19: 26042.3 | H19: =G19/G18-1 -> 0.0029230082 | J19: Adjusted Beta | K19: =(K13*K14)+(K16*K17) -> 0.91951686
B20: 46019 | C20: 1592.3 | D20: =C20/C19-1 -> 0.021228835 | F20: 46019 | G20: 26328.55 | H20: =G20/G19-1 -> 0.010991733
B21: 46026 | C21: 1475.3 | D21: =C21/C20-1 -> -0.073478616 | F21: 46026 | G21: 25683.3 | H21: =G21/G20-1 -> -0.024507616 | J21: SUMMARY OUTPUT
B22: 46033 | C22: 1457.9 | D22: =C22/C21-1 -> -0.011794211 | F22: 46033 | G22: 25694.35 | H22: =G22/G21-1 -> 0.00043024066
B23: 46040 | C23: 1386.1 | D23: =C23/C22-1 -> -0.04924892 | F23: 46040 | G23: 25048.65 | H23: =G23/G22-1 -> -0.025130038 | J23: Regression Statistics
B24: 46047 | C24: 1395.4 | D24: =C24/C23-1 -> 0.0067094726 | F24: 46047 | G24: 25320.65 | H24: =G24/G23-1 -> 0.010858869 | J24: Multiple R | K24: 0.54136003
B25: 46054 | C25: 1450.8 | D25: =C25/C24-1 -> 0.039701878 | F25: 46054 | G25: 25693.7 | H25: =G25/G24-1 -> 0.014733034 | J25: R Square | K25: 0.29307068
B26: 46061 | C26: 1419.6 | D26: =C26/C25-1 -> -0.021505376 | F26: 46061 | G26: 25471.1 | H26: =G26/G25-1 -> -0.0086636024 | J26: Adjusted R Square | K26: 0.27864355
B27: 46068 | C27: 1419.4 | D27: =C27/C26-1 -> -0.00014088476 | F27: 46068 | G27: 25571.25 | H27: =G27/G26-1 -> 0.0039319071 | J27: Standard Error | K27: 0.023415769
B28: 46075 | C28: 1393.9 | D28: =C28/C27-1 -> -0.017965337 | F28: 46075 | G28: 25178.65 | H28: =G28/G27-1 -> -0.01535318 | J28: Observations | K28: 51
B29: 46082 | C29: 1404.8 | D29: =C29/C28-1 -> 0.0078197862 | F29: 46082 | G29: 24450.45 | H29: =G29/G28-1 -> -0.028921328
B30: 46089 | C30: 1380.7 | D30: =C30/C29-1 -> -0.017155467 | F30: 46089 | G30: 23151.1 | H30: =G30/G29-1 -> -0.053142171 | J30: ANOVA
B31: 46096 | C31: 1414.4 | D31: =C31/C30-1 -> 0.024407909 | F31: 46096 | G31: 23114.5 | H31: =G31/G30-1 -> -0.0015809184 | K31: df | L31: SS | M31: MS | N31: F | O31: Significance F
B32: 46103 | C32: 1348.1 | D32: =C32/C31-1 -> -0.046875 | F32: 46103 | G32: 22819.6 | H32: =G32/G31-1 -> -0.012758225 | J32: Regression | K32: 1 | L32: 0.011138054 | M32: 0.011138054 | N32: 20.31386 | O32: 4.094893e-05
B33: 46110 | C33: 1350.5 | D33: =C33/C32-1 -> 0.0017802834 | F33: 46110 | G33: 22713.1 | H33: =G33/G32-1 -> -0.0046670406 | J33: Residual | K33: 49 | L33: 0.026866614 | M33: 0.00054829824
B34: 46117 | C34: 1350.2 | D34: =C34/C33-1 -> -0.00022213995 | F34: 46117 | G34: 24050.6 | H34: =G34/G33-1 -> 0.058886722 | J34: Total | K34: 50 | L34: 0.038004668
B35: 46124 | C35: 1365 | D35: =C35/C34-1 -> 0.010961339 | F35: 46124 | G35: 24353.55 | H35: =G35/G34-1 -> 0.012596359
B36: 46131 | C36: 1327.8 | D36: =C36/C35-1 -> -0.027252747 | F36: 46131 | G36: 23897.95 | H36: =G36/G35-1 -> -0.018707745 | K36: Coefficients | L36: Standard Error | M36: t Stat | N36: P-value | O36: Lower 95% | P36: Upper 95% | Q36: Lower 95.0% | R36: Upper 95.0%
B37: 46138 | C37: 1430.8 | D37: =C37/C36-1 -> 0.077571923 | F37: 46138 | G37: 23997.55 | H37: =G37/G36-1 -> 0.0041677215 | J37: Intercept | K37: -0.00054921948 | L37: 0.003288871 | M37: -0.16699332 | N37: 0.86806256 | O37: -0.0071584532 | P37: 0.0060600142 | Q37: -0.0071584532 | R37: 0.0060600142
B38: 46145 | C38: 1435.2 | D38: =C38/C37-1 -> 0.0030752027 | F38: 46145 | G38: 24176.15 | H38: =G38/G37-1 -> 0.0074424264 | J38: X Variable 1 | K38: 0.89268915 | L38: 0.19806331 | M38: 4.50709 | N38: 4.094893e-05 | O38: 0.49466603 | P38: 1.2907123 | Q38: 0.49466603 | R38: 1.2907123
B39: 46152 | C39: 1336.4 | D39: =C39/C38-1 -> -0.06884058 | F39: 46152 | G39: 23643.5 | H39: =G39/G38-1 -> -0.022032044
B40: 46159 | C40: 1354.5 | D40: =C40/C39-1 -> 0.013543849 | F40: 46159 | G40: 23719.3 | H40: =G40/G39-1 -> 0.0032059551
B41: 46166 | C41: 1321.2 | D41: =C41/C40-1 -> -0.024584718 | F41: 46166 | G41: 23547.75 | H41: =G41/G40-1 -> -0.0072325069
B42: 46173 | C42: 1291 | D42: =C42/C41-1 -> -0.022858008 | F42: 46173 | G42: 23366.7 | H42: =G42/G41-1 -> -0.0076886327
B43: 46180 | C43: 1293 | D43: =C43/C42-1 -> 0.0015491867 | F43: 46180 | G43: 23622.9 | H43: =G43/G42-1 -> 0.010964321
B44: 46187 | C44: 1309.5 | D44: =C44/C43-1 -> 0.012761021 | F44: 46187 | G44: 24013.1 | H44: =G44/G43-1 -> 0.01651787
B45: 46194 | C45: 1318.1 | D45: =C45/C44-1 -> 0.0065673921 | F45: 46194 | G45: 24056 | H45: =G45/G44-1 -> 0.0017865249
B46: 46201 | C46: 1304 | D46: =C46/C45-1 -> -0.010697216 | F46: 46201 | G46: 24270.85 | H46: =G46/G45-1 -> 0.0089312438
B47: 46208 | C47: 1307.8 | D47: =C47/C46-1 -> 0.0029141104 | F47: 46208 | G47: 24206.9 | H47: =G47/G46-1 -> -0.002634848
B48: 46215 | C48: 1327.2 | D48: =C48/C47-1 -> 0.014834072 | F48: 46215 | G48: 24334.3 | H48: =G48/G47-1 -> 0.0052629622
B49: 46222 | C49: 1278 | D49: =C49/C48-1 -> -0.037070524 | F49: 46222 | G49: 23767.45 | H49: =G49/G48-1 -> -0.02329428
B50: 46229 | C50: 1307.8 | D50: =C50/C49-1 -> 0.023317684 | F50: 46229 | G50: 24383.6 | H50: =G50/G49-1 -> 0.02592411
... B58: 46285 | C58: 1226 | D58: =C58/C57-1 -> -0.00032615786 | F58: 46285 | G58: 23140.5 | H58: =G58/G57-1 -> -0.0088193469
B61: Indain Oil Corporation Ltd | F61: Nifty 50 Return | J61: Beta Calulation
B63: Date | C63: Closing Price | D63: Return | F63: Date | G63: Closing Price | H63: Return
B64: 45928 | C64: 150.39 | F64: 45928 | G64: 24894.25 | J64: Beta 1 (Slope) | K64: =SLOPE(D65:D115,H65:H115) -> 1.3213055
B65: 45935 | C65: 154.11 | D65: =C65/C64-1 -> 0.024735687 | F65: 45935 | G65: 25285.35 | H65: =G65/G64-1 -> 0.015710455 | J65: Beta 2 (Covariance) | K65: {=_xlfn.COVARIANCE.S(D65:D115,H65:H115/_xlfn.VAR.S(H65:H115))} -> 1.3213055
B66: 45942 | C66: 152.91 | D66: =C66/C65-1 -> -0.0077866459 | F66: 45942 | G66: 25709.85 | H66: =G66/G65-1 -> 0.016788377 | J66: Beta 3 (Linear Regression) | K66: =K96 -> 1.3213055
B67: 45949 | C67: 150.37 | D67: =C67/C66-1 -> -0.016611078 | F67: 45949 | G67: 25795.15 | H67: =G67/G66-1 -> 0.0033177945
B68: 45956 | C68: 165.9 | D68: =C68/C67-1 -> 0.10327858 | F68: 45956 | G68: 25722.1 | H68: =G68/G67-1 -> -0.0028319277 | J68: Beta Drifting
B69: 45963 | C69: 169.16 | D69: =C69/C68-1 -> 0.019650392 | F69: 45963 | G69: 25492.3 | H69: =G69/G68-1 -> -0.0089339517
B70: 45970 | C70: 171.25 | D70: =C70/C69-1 -> 0.012355167 | F70: 45970 | G70: 25910.05 | H70: =G70/G69-1 -> 0.016387301 | J70: levered Raw Beta | K70: =K66 -> 1.3213055
B71: 45977 | C71: 167.35 | D71: =C71/C70-1 -> -0.022773723 | F71: 45977 | G71: 26068.15 | H71: =G71/G70-1 -> 0.0061018794 | J71: Raw Beta Weight | K71: 0.75
B72: 45984 | C72: 161.75 | D72: =C72/C71-1 -> -0.033462803 | F72: 45984 | G72: 26202.95 | H72: =G72/G71-1 -> 0.0051710612
B73: 45991 | C73: 163.66 | D73: =C73/C72-1 -> 0.011808346 | F73: 45991 | G73: 26186.45 | H73: =G73/G72-1 -> -0.00062970009 | J73: Market Beta | K73: 1
B74: 45998 | C74: 163.67 | D74: =C74/C73-1 -> 6.1102285e-05 | F74: 45998 | G74: 26046.95 | H74: =G74/G73-1 -> -0.0053271826 | J74: Market Beta Weight | K74: 0.25
B75: 46005 | C75: 162.6 | D75: =C75/C74-1 -> -0.0065375451 | F75: 46005 | G75: 25966.4 | H75: =G75/G74-1 -> -0.0030924926
B76: 46012 | C76: 160.3 | D76: =C76/C75-1 -> -0.014145141 | F76: 46012 | G76: 26042.3 | H76: =G76/G75-1 -> 0.0029230082 | J76: Adjusted Beta | K76: =(K70*K71)+(K73*K74) -> 1.2409791
B77: 46019 | C77: 166.79 | D77: =C77/C76-1 -> 0.040486588 | F77: 46019 | G77: 26328.55 | H77: =G77/G76-1 -> 0.010991733
B78: 46026 | C78: 157.61 | D78: =C78/C77-1 -> -0.055039271 | F78: 46026 | G78: 25683.3 | H78: =G78/G77-1 -> -0.024507616
B79: 46033 | C79: 161.32 | D79: =C79/C78-1 -> 0.023539116 | F79: 46033 | G79: 25694.35 | H79: =G79/G78-1 -> 0.00043024066 | J79: SUMMARY OUTPUT
B80: 46040 | C80: 156.03 | D80: =C80/C79-1 -> -0.032791966 | F80: 46040 | G80: 25048.65 | H80: =G80/G79-1 -> -0.025130038
B81: 46047 | C81: 163.24 | D81: =C81/C80-1 -> 0.046209062 | F81: 46047 | G81: 25320.65 | H81: =G81/G80-1 -> 0.010858869 | J81: Regression Statistics
B82: 46054 | C82: 175.2 | D82: =C82/C81-1 -> 0.073266356 | F82: 46054 | G82: 25693.7 | H82: =G82/G81-1 -> 0.014733034 | J82: Multiple R | K82: 0.56893459
B83: 46061 | C83: 176.77 | D83: =C83/C82-1 -> 0.0089611872 | F83: 46061 | G83: 25471.1 | H83: =G83/G82-1 -> -0.0086636024 | J83: R Square | K83: 0.32368657
B84: 46068 | C84: 173.79 | D84: =C84/C83-1 -> -0.016858064 | F84: 46068 | G84: 25571.25 | H84: =G84/G83-1 -> 0.0039319071 | J84: Adjusted R Square | K84: 0.30988426
B85: 46075 | C85: 187.47 | D85: =C85/C84-1 -> 0.078715691 | F85: 46075 | G85: 25178.65 | H85: =G85/G84-1 -> -0.01535318 | J85: Standard Error | K85: 0.0322568
B86: 46082 | C86: 168.68 | D86: =C86/C85-1 -> -0.10022937 | F86: 46082 | G86: 24450.45 | H86: =G86/G85-1 -> -0.028921328 | J86: Observations | K86: 51
B87: 46089 | C87: 156.54 | D87: =C87/C86-1 -> -0.071970595 | F87: 46089 | G87: 23151.1 | H87: =G87/G86-1 -> -0.053142171
B88: 46096 | C88: 144.6 | D88: =C88/C87-1 -> -0.076274435 | F88: 46096 | G88: 23114.5 | H88: =G88/G87-1 -> -0.0015809184 | J88: ANOVA
B89: 46103 | C89: 137.76 | D89: =C89/C88-1 -> -0.047302905 | F89: 46103 | G89: 22819.6 | H89: =G89/G88-1 -> -0.012758225 | K89: df | L89: SS | M89: MS | N89: F | O89: Significance F
B90: 46110 | C90: 134.13 | D90: =C90/C89-1 -> -0.026350174 | F90: 46110 | G90: 22713.1 | H90: =G90/G89-1 -> -0.0046670406 | J90: Regression | K90: 1 | L90: 0.024401432 | M90: 0.024401432 | N90: 23.451615 | O90: 1.3239707e-05
B91: 46117 | C91: 142.96 | D91: =C91/C90-1 -> 0.065831656 | F91: 46117 | G91: 24050.6 | H91: =G91/G90-1 -> 0.058886722 | J91: Residual | K91: 49 | L91: 0.050984555 | M91: 0.0010405011
B92: 46124 | C92: 145.88 | D92: =C92/C91-1 -> 0.020425294 | F92: 46124 | G92: 24353.55 | H92: =G92/G91-1 -> 0.012596359 | J92: Total | K92: 50 | L92: 0.075385987
B93: 46131 | C93: 143.47 | D93: =C93/C92-1 -> -0.016520428 | F93: 46131 | G93: 23897.95 | H93: =G93/G92-1 -> -0.018707745
B94: 46138 | C94: 142.25 | D94: =C94/C93-1 -> -0.0085035199 | F94: 46138 | G94: 23997.55 | H94: =G94/G93-1 -> 0.0041677215 | K94: Coefficients | L94: Standard Error | M94: t Stat | N94: P-value | O94: Lower 95% | P94: Upper 95% | Q94: Lower 95.0% | R94: Upper 95.0%
B95: 46145 | C95: 144.69 | D95: =C95/C94-1 -> 0.0171529 | F95: 46145 | G95: 24176.15 | H95: =G95/G94-1 -> 0.0074424264 | J95: Intercept | K95: 0.00043723001 | L95: 0.0045306414 | M95: 0.096505101 | N95: 0.92351306 | O95: -0.0086674348 | P95: 0.0095418949 | Q95: -0.0086674348 | R95: 0.0095418949
B96: 46152 | C96: 134.48 | D96: =C96/C95-1 -> -0.070564655 | F96: 46152 | G96: 23643.5 | H96: =G96/G95-1 -> -0.022032044 | J96: X Variable 1 | K96: 1.3213055 | L96: 0.27284555 | M96: 4.8426868 | N96: 1.3239707e-05 | O96: 0.77300187 | P96: 1.8696092 | Q96: 0.77300187 | R96: 1.8696092
B97: 46159 | C97: 139.47 | D97: =C97/C96-1 -> 0.037105889 | F97: 46159 | G97: 23719.3 | H97: =G97/G96-1 -> 0.0032059551
B98: 46166 | C98: 140.24 | D98: =C98/C97-1 -> 0.0055209006 | F98: 46166 | G98: 23547.75 | H98: =G98/G97-1 -> -0.0072325069
B99: 46173 | C99: 138.26 | D99: =C99/C98-1 -> -0.014118654 | F99: 46173 | G99: 23366.7 | H99: =G99/G98-1 -> -0.0076886327
B100: 46180 | C100: 140.94 | D100: =C100/C99-1 -> 0.01938377 | F100: 46180 | G100: 23622.9 | H100: =G100/G99-1 -> 0.010964321
B101: 46187 | C101: 143.43 | D101: =C101/C100-1 -> 0.017667092 | F101: 46187 | G101: 24013.1 | H101: =G101/G100-1 -> 0.01651787
B102: 46194 | C102: 143.89 | D102: =C102/C101-1 -> 0.0032071394 | F102: 46194 | G102: 24056 | H102: =G102/G101-1 -> 0.0017865249
B103: 46201 | C103: 141.56 | D103: =C103/C102-1 -> -0.016192925 | F103: 46201 | G103: 24270.85 | H103: =G103/G102-1 -> 0.0089312438
B104: 46208 | C104: 138.96 | D104: =C104/C103-1 -> -0.01836677 | F104: 46208 | G104: 24206.9 | H104: =G104/G103-1 -> -0.002634848
B105: 46215 | C105: 141.69 | D105: =C105/C104-1 -> 0.019645941 | F105: 46215 | G105: 24334.3 | H105: =G105/G104-1 -> 0.0052629622
B106: 46222 | C106: 138.47 | D106: =C106/C105-1 -> -0.022725669 | F106: 46222 | G106: 23767.45 | H106: =G106/G105-1 -> -0.02329428
B107: 46229 | C107: 140.17 | D107: =C107/C106-1 -> 0.012277028 | F107: 46229 | G107: 24383.6 | H107: =G107/G106-1 -> 0.02592411
B108: 46236 | C108: 143.38 | D108: =C108/C107-1 -> 0.022900763 | F108: 46236 | G108: 24570.65 | H108: =G108/G107-1 -> 0.0076711396
... B115: 46285 | C115: 135.7 | D115: =C115/C114-1 -> -0.0094890511 | F115: 46285 | G115: 23140.5 | H115: =G115/G114-1 -> -0.0088193469
B118: Bharat petroleum Corporation Ltd | F118: Nifty 50 Return | J118: Beta Calulation
B120: Date | C120: Closing Price | D120: Return | F120: Date | G120: Closing Price | H120: Return
B121: 45928 | C121: 341.55 | F121: 45928 | G121: 24894.25 | J121: Beta 1 (Slope) | K121: =SLOPE(D122:D172,H122:H172) -> 1.462644
B122: 45935 | C122: 338.7 | D122: =C122/C121-1 -> -0.0083443127 | F122: 45935 | G122: 25285.35 | H122: =G122/G121-1 -> 0.015710455 | J122: Beta 2 (Covariance) | K122: {=_xlfn.COVARIANCE.S(D122:D172,H122:H172/_xlfn.VAR.S(H122:H172))} -> 1.462644
B123: 45942 | C123: 335.85 | D123: =C123/C122-1 -> -0.0084145261 | F123: 45942 | G123: 25709.85 | H123: =G123/G122-1 -> 0.016788377 | J123: Beta 3 (Linear Regression) | K123: =K154 -> 1.462644
...

Sheet AVG Return
B3: Year | C3: Annual | D3: Return
B4: 2000 | C4: -14.65
B5: 2001 | C5: -16.18 | D5: =(C5/C4-1)/100 -> 0.0010443686 | G5: Average Return | I5: =(AVERAGE(C4:C29))/100 -> 0.15149231
B6: 2002 | C6: 3.25 | D6: =(C6/C5-1)/100 -> -0.012008653 | G6: Dividend yield | I6: 0.013
B7: 2003 | C7: 71.9 | D7: =(C7/C6-1)/100 -> 0.21123077
B8: 2004 | C8: 10.68 | D8: =(C8/C7-1)/100 -> -0.0085146036 | G8: Total Msrket Return | I8: =SUM(I5:I6) -> 0.16449231
B9: 2005 | C9: 36.34 | D9: =(C9/C8-1)/100 -> 0.024026217
B10: 2006 | C10: 39.83 | D10: =(C10/C9-1)/100 -> 0.00096037424
B11: 2007 | C11: 54.77 | D11: =(C11/C10-1)/100 -> 0.0037509415
B12: 2008 | C12: -51.79 | D12: =(C12/C11-1)/100 -> -0.019455907
B13: 2009 | C13: 75.76 | D13: =(C13/C12-1)/100 -> -0.024628307
B14: 2010 | C14: 17.95 | D14: =(C14/C13-1)/100 -> -0.0076306758
B15: 2011 | C15: -24.62 | D15: =(C15/C14-1)/100 -> -0.023715877
B16: 2012 | C16: 27.7 | D16: =(C16/C15-1)/100 -> -0.021251015
B17: 2013 | C17: 6.76 | D17: =(C17/C16-1)/100 -> -0.0075595668
B18: 2014 | C18: 31.39 | D18: =(C18/C17-1)/100 -> 0.036434911
B19: 2015 | C19: -4.06 | D19: =(C19/C18-1)/100 -> -0.011293406
B20: 2016 | C20: 3.01 | D20: =(C20/C19-1)/100 -> -0.017413793
... B29: 2025 | C29: 10.51 | D29: =(C29/C28-1)/100 -> 0.0020114286
